Workbook

Sheet Data
A1: Day | B1: Monto | C1: Detalle | D1: Clasificacion | E1: Checker | F1: Check Class | G1: Check Monto
A2: 1 | C2: Luz | D2: Luz | E2: =if(and(F2,G2),1,2) -> 2 | F2: =ISBLANK(D2) -> FALSE | G2: =ISNUMBER(B2) -> FALSE
A3: 1 | B3: 37 | C3: ChatGPT | D3: Otros Personales | E3: =if(and(F3,G3),1,2) -> 2 | F3: =ISBLANK(D3) -> FALSE | G3: =ISNUMBER(B3) -> TRUE
A4: 1 | B4: 95 | C4: Internet | D4: Internet | E4: =if(and(F4,G4),1,2) -> 2 | F4: =ISBLANK(D4) -> FALSE | G4: =ISNUMBER(B4) -> TRUE
A5: 1 | B5: 33 | C5: DogDown Yoga App | D5: Otros Personales | E5: =if(and(F5,G5),1,2) -> 2 | F5: =ISBLANK(D5) -> FALSE | G5: =ISNUMBER(B5) -> TRUE
A6: 1 | B6: 27 | C6: Youtube - Suscripción x2 | D6: Otros Personales | E6: =if(and(F6,G6),1,2) -> 2 | F6: =ISBLANK(D6) -> FALSE | G6: =ISNUMBER(B6) -> TRUE
A7: 1 | B7: 34 | C7: Claude Pro | D7: Otros Personales
A8: 2 | B8: 200.67 | C8: Declaraciones Renta Chile 2026 x2 | D8: Otros Personales
A9: 2 | B9: 90 | C9: Uniqlo - Ropa Pato | D9: Ropa - Accesorios
A10: 2 | B10: 50 | C10: Uniqlo - Regalos | D10: Regalos - Eventos
A11: 2 | B11: 33 | C11: Haketama - Ramen Chermise | D11: Almuerzo
A12: 2 | B12: 6 | C12: Brazzos - Pudin | D12: Almuerzo
A13: 2 | B13: 88 | C13: Kmart - Pijamas | D13: Ropa - Accesorios
A14: 2 | B14: 110 | C14: Wollies | D14: Super
A15: 2 | B15: 6 | C15: Parking Chermise | D15: Estacionamiento - CarWash
A16: 3 | B16: 22 | C16: Christian Jaques - Croissant y Pan | D16: Desayuno
A17: 4 | B17: 67 | C17: Loose Moose Lunch | D17: Almuerzo
A18: 4 | B18: 18 | C18: Yochi | D18: Almuerzo
... A64: 25 | B64: 21 | C64: Linkt Peajes | D64: Peajes
A65: 27 | B65: 33 | C65: Cursor Suscription | D65: Otros Personales | E65: =if(and(F65,G65),1,2) -> 2 | F65: =ISBLANK(D65) -> FALSE | G65: =ISNUMBER(B65) -> TRUE
A66: 28 | B66: 80 | C66: Carga Golinkt | D66: Tren - GoCard - Scooter Pega | E66: =if(and(F66,G66),1,2) -> 2 | F66: =ISBLANK(D66) -> FALSE | G66: =ISNUMBER(B66) -> TRUE
A67: 28 | B67: 16 | C67: Burger King - Jueves | D67: Cena | E67: =if(and(F67,G67),1,2) -> 2 | F67: =ISBLANK(D67) -> FALSE | G67: =ISNUMBER(B67) -> TRUE
A68: 28 | B68: 3 | C68: Lime - Jueves | D68: Tren - GoCard - Scooter Pega | E68: =if(and(F68,G68),1,2) -> 2 | F68: =ISBLANK(D68) -> FALSE | G68: =ISNUMBER(B68) -> TRUE
A69: 25 | B69: 31 | C69: Uber eats - Almuerzo Vale | D69: Almuerzo | E69: =if(and(F69,G69),1,2) -> 2 | F69: =ISBLANK(D69) -> FALSE | G69: =ISNUMBER(B69) -> TRUE
A70: 27 | B70: 9 | C70: Christian Jacques - Croissant | D70: Desayuno | E70: =if(and(F70,G70),1,2) -> 2 | F70: =ISBLANK(D70) -> FALSE | G70: =ISNUMBER(B70) -> TRUE
A71: 29 | B71: 34 | C71: Hakataya - Ramen | D71: Almuerzo | E71: =if(and(F71,G71),1,2) -> 2 | F71: =ISBLANK(D71) -> FALSE | G71: =ISNUMBER(B71) -> TRUE
A72: 29 | B72: 14 | C72: Starbucks | D72: Cena | E72: =if(and(F72,G72),1,2) -> 2 | F72: =ISBLANK(D72) -> FALSE | G72: =ISNUMBER(B72) -> TRUE
A73: 29 | B73: 185 | C73: Coles - Pizzas | D73: Super | E73: =if(and(F73,G73),1,2) -> 2 | F73: =ISBLANK(D73) -> FALSE | G73: =ISNUMBER(B73) -> TRUE
A74: 30 | B74: 56 | C74: Corte Pelo | D74: Corte Pelo - Salud - Remedios | E74: =if(and(F74,G74),1,2) -> 2 | F74: =ISBLANK(D74) -> FALSE | G74: =ISNUMBER(B74) -> TRUE
A75: 30 | B75: 7 | C75: OfficeWorks - Print | D75: Otros Personales | E75: =if(and(F75,G75),1,2) -> 2 | F75: =ISBLANK(D75) -> FALSE | G75: =ISNUMBER(B75) -> TRUE
A76: 31 | B76: 22 | C76: Christian Jaques - Pan y Croissant | D76: Desayuno+ | E76: =if(and(F76,G76),1,2) -> 2 | F76: =ISBLANK(D76) -> FALSE | G76: =ISNUMBER(B76) -> TRUE
A77: 31 | B77: 50 | C77: Uber Pega | D77: Uber Pega | E77: =if(and(F77,G77),1,2) -> 2 | F77: =ISBLANK(D77) -> FALSE | G77: =ISNUMBER(B77) -> TRUE
E78: =if(and(F78,G78),1,2) -> 2 | F78: =ISBLANK(D78) -> TRUE | G78: =ISNUMBER(B78) -> FALSE
E79: =if(and(F79,G79),1,2) -> 2 | F79: =ISBLANK(D79) -> TRUE | G79: =ISNUMBER(B79) -> FALSE
E80: =if(and(F80,G80),1,2) -> 2 | F80: =ISBLANK(D80) -> TRUE | G80: =ISNUMBER(B80) -> FALSE
E81: =if(and(F81,G81),1,2) -> 2 | F81: =ISBLANK(D81) -> TRUE | G81: =ISNUMBER(B81) -> FALSE
E82: =if(and(F82,G82),1,2) -> 2 | F82: =ISBLANK(D82) -> TRUE | G82: =ISNUMBER(B82) -> FALSE
E83: =if(and(F83,G83),1,2) -> 2 | F83: =ISBLANK(D83) -> TRUE | G83: =ISNUMBER(B83) -> FALSE
E84: =if(and(F84,G84),1,2) -> 2 | F84: =ISBLANK(D84) -> TRUE | G84: =ISNUMBER(B84) -> FALSE
E85: =if(and(F85,G85),1,2) -> 2 | F85: =ISBLANK(D85) -> TRUE | G85: =ISNUMBER(B85) -> FALSE
E86: =if(and(F86,G86),1,2) -> 2 | F86: =ISBLANK(D86) -> TRUE | G86: =ISNUMBER(B86) -> FALSE
E87: =if(and(F87,G87),1,2) -> 2 | F87: =ISBLANK(D87) -> TRUE | G87: =ISNUMBER(B87) -> FALSE
E88: =if(and(F88,G88),1,2) -> 2 | F88: =ISBLANK(D88) -> TRUE | G88: =ISNUMBER(B88) -> FALSE
E89: =if(and(F89,G89),1,2) -> 2 | F89: =ISBLANK(D89) -> TRUE | G89: =ISNUMBER(B89) -> FALSE
... E100: =if(and(F100,G100),1,2) -> 2 | F100: =ISBLANK(D100) -> TRUE | G100: =ISNUMBER(B100) -> FALSE

Sheet Graficos
A1: 31 | R1: Dia
R2: =Acumulado!AJ59 -> 31 | S2: MTD | T2: Rem. Mes | U2: Balance Proyectado
R3: Internet | S3: =Acumulado!AM216 -> -7 | T3: =Acumulado!AN216 -> -7 | U3: -14
R4: Comidas | S4: =Acumulado!AM218 -> 61 | T4: =Acumulado!AN218 -> 61 | U4: 122
R5: Super | S5: =Acumulado!AM221 -> -221 | T5: =Acumulado!AN221 -> -221 | U5: -442
R6: Otros Casa | S6: =Acumulado!AM222 -> 387 | T6: =Acumulado!AN222 -> 387 | U6: 774
R7: Corte Pelo | S7: =Acumulado!AM223 -> -12 | T7: =Acumulado!AN223 -> -12 | U7: -24
R8: Transporte BNE | S8: =Acumulado!AM225 -> 150 | T8: =Acumulado!AN225 -> 150 | U8: 300
R9: Auto | S9: =Acumulado!AM227 -> 145 | T9: =Acumulado!AN227 -> 145 | U9: 290
R10: Gastos Pega | S10: =Acumulado!AM233 -> 164.8 | T10: =Acumulado!AN233 -> 164.8 | U10: 329.6
R11: Otros Personales | S11: =Acumulado!AM236 -> -292.67 | T11: =Acumulado!AN236 -> -292.67 | U11: -585.34
S12: =SUM(S3:S11) -> 375.13 | T12: =SUM(T3:T11) -> 375.13 | U12: 750.26
R13: Total % Acum.
R14: =Acumulado!D192 -> 0.8810546
S15: Item
S16: Luz | T16: Mecanico | U16: REGO | V16: Viajes | W16: Otros Fuera Presupuesto | X16: Obs: | Z16: Total Mensual | AA16: Caja Presupuesto | AB16: % | AC16: Balance Caja | AD16: Sin Gasto Unico | AE16: Ingreso Extra | AF16: Obs:
R17: Enero | S17: 450.11 | T17: 0 | U17: 0 | V17: 0 | W17: 0 | Z17: =SUM(S17:W17)*-1 -> -450.11 | AA17: -136.8 | AB17: 1.0433762 | AC17: -586.91 | AD17: -586.91
R18: Febrero | S18: 0 | T18: 6943 | U18: 0 | V18: 340 | W18: 0 | X18: Viaje Coolangatta (340) / Reparacion Auto (6943) | Z18: =SUM(S18:W18)*-1 -> -7283 | AA18: -1 | AB18: 1 | AC18: -7284 | AD18: -7284 | AE18: 14000 | AF18: Bono Glencore
R19: Marzo | S19: 0 | T19: 0 | U19: 437 | V19: 0 | W19: 0 | X19: REGO Mazda 6 months | Z19: =SUM(S19:W19)*-1 -> -437 | AA19: 893 | AB19: 0.72 | AC19: 456 | AD19: 456
R20: Abril | S20: 487 | T20: 0 | U20: 0 | V20: 0 | W20: 1466 | X20: Luz 3 Meses / Celular S24 Pato (723) / BVB (743) | Z20: =SUM(S20:W20)*-1 -> -1953 | AA20: 496.99452 | AB20: 0.8371612 | AC20: -1456.0055 | AD20: -1456.0055
R21: Mayo | S21: =SUMIF(Data!$D$2:$D$100,S$16,Data!$B$2:$B$100) -> 0 | T21: =SUMIF(Data!$D$2:$D$100,T$16,Data!$B$2:$B$100) -> 0 | U21: =SUMIF(Data!$D$2:$D$100,U$16,Data!$B$2:$B$100) -> 0 | V21: =SUMIF(Data!$D$2:$D$100,V$16,Data!$B$2:$B$100) -> 0 | W21: =SUMIF(Data!$D$2:$D$100,W$16,Data!$B$2:$B$100) -> 660 | X21: Fragomen Reu (660) | Z21: =SUM(S21:W21)*-1 -> -660 | AA21: =$S$12 -> 375.13 | AB21: =Acumulado!$D$192 -> 0.8810546 | AC21: -284.87 | AD21: -284.87
R22: Junio | S22: 412.5 | Z22: =SUM(S22:W22)*-1 -> -412.5 | AC22: -412.5 | AD22: -412.5
R23: Julio | Z23: =SUM(S23:W23)*-1 -> 0 | AC23: 0 | AD23: 0
R24: Agosto | Z24: =SUM(S24:W24)*-1 -> 0 | AC24: 0 | AD24: 0
R25: Septiembre | S25: 412.5 | Z25: =SUM(S25:W25)*-1 -> -412.5 | AC25: -412.5 | AD25: -412.5
R26: Octubre | T26: 600 | U26: 450 | Z26: =SUM(S26:W26)*-1 -> -1050 | AC26: -1050 | AD26: -1050
R27: Noviembre | Z27: =SUM(S27:W27)*-1 -> 0 | AC27: 0 | AD27: 0
R28: Diciembre | S28: 412.5 | V28: 3000 | Z28: =SUM(S28:W28)*-1 -> -3412.5 | AC28: -3412.5 | AD28: -3412.5
R29: Gasto Año | S29: =SUM(S17:S28) -> 2174.61 | T29: =SUM(T17:T28) -> 7543 | U29: =SUM(U17:U28) -> 887 | V29: =SUM(V17:V28) -> 3340 | W29: =SUM(W17:W28) -> 2126 | Z29: =SUM(S29:W29) -> 16070.61 | AA29: =SUM(AA17:AA28) -> 1627.3245 | AB29: =AVERAGE(AB17:AB28) -> 0.89631841 | AC29: -14443.285 | AD29: -14443.285 | AE29: 14000 | AF29: 0
R30: Presupuesto | S30: =Presupuesto!F7/4*3 -> 1649.7 | T30: =Presupuesto!F39 -> 600 | U30: =Presupuesto!F40 -> 900 | V30: =Presupuesto!F54 -> 3000 | W30: 0 | Z30: =SUM(S30:W30) -> 6149.7
R31: Diferencia | S31: =S30-S29 -> -524.91 | T31: =T30-T29 -> -6943 | U31: =U30-U29 -> 13 | V31: =V30-V29 -> -340 | W31: =W30-W29 -> -2126 | Z31: =SUM(S31:W31) -> -9920.91 | AA31: -8293.5855
R32: Diff x Mes | S32: =S31/12 -> -43.7425 | T32: =T31/12 -> -578.58333 | U32: =U31/12 -> 1.0833333 | V32: =V31/12 -> -28.333333 | W32: =W31/12 -> -177.16667 | Z32: =SUM(S32:W32) -> -826.7425 | AA32: =AA31/12 -> -691.13212
AA34: Balance vs Budget | AB34: vs BP sin extras
Z35: Anual | AA35: =Z31+AA29+AE29 -> 5706.4145 | AB35: =AA35-W31 -> 7832.4145
Z36: Mensual | AA36: =AA35/12 -> 475.53454 | AB36: =AB35/12 -> 652.70121
R38: Otros Fuera Presupuesto
R39: Motivo | S39: Item | T39: Monto | U39: Status | V39: Obs.
S40: Total | T40: =SUM(T41:T55) -> 8937
R41: Viaje Ricardo-Paty | S41: Vuelos SLC-BNE | T41: 3675 | U41: Pagado | W41: =IF(U41="Pagado",1,IF(U41="Solo Cotizado",2,IF(U41="Reservado no Pagado",3,4))) -> 1
R42: Viaje Ricardo-Paty | S42: Hotel Hobart | T42: 996 | U42: Pagado | W42: =IF(U42="Pagado",1,IF(U42="Solo Cotizado",2,IF(U42="Reservado no Pagado",3,4))) -> 1
R43: Viaje Ricardo-Paty | S43: Hotel Melbourne | T43: 675 | U43: Pagado | W43: =IF(U43="Pagado",1,IF(U43="Solo Cotizado",2,IF(U43="Reservado no Pagado",3,4))) -> 1
R44: Viaje Ricardo-Paty | S44: Vuelo BNE - HBA / MEL - BNE | T44: 1147 | U44: Pagado | W44: =IF(U44="Pagado",1,IF(U44="Solo Cotizado",2,IF(U44="Reservado no Pagado",3,4))) -> 1
R45: Viaje Ricardo-Paty | W45: =IF(U45="Pagado",1,IF(U45="Solo Cotizado",2,IF(U45="Reservado no Pagado",3,4))) -> 4
R46: Viaje Ricardo-Paty | S46: Rent a Car - 5 Dias | T46: 942 | U46: Pagado | W46: =IF(U46="Pagado",1,IF(U46="Solo Cotizado",2,IF(U46="Reservado no Pagado",3,4))) -> 1
R47: Viaje Ricardo-Paty | S47: Ferry HBA - MEL | T47: 726 | U47: Pagado | W47: =IF(U47="Pagado",1,IF(U47="Solo Cotizado",2,IF(U47="Reservado no Pagado",3,4))) -> 1
R48: Viaje Ricardo-Paty | W48: =IF(U48="Pagado",1,IF(U48="Solo Cotizado",2,IF(U48="Reservado no Pagado",3,4))) -> 4
R49: Viaje Ricardo-Paty | S49: Reserva AOS | T49: 356 | U49: Pagado | W49: =IF(U49="Pagado",1,IF(U49="Solo Cotizado",2,IF(U49="Reservado no Pagado",3,4))) -> 1
R50: Viaje Ricardo-Paty | S50: Horse Darling Downs | W50: =IF(U50="Pagado",1,IF(U50="Solo Cotizado",2,IF(U50="Reservado no Pagado",3,4))) -> 4
R51: Viaje Ricardo-Paty | S51: Reserva QPAC | W51: =IF(U51="Pagado",1,IF(U51="Solo Cotizado",2,IF(U51="Reservado no Pagado",3,4))) -> 4
R52: Viaje Ricardo-Paty | S52: Puffing Train | T52: 256 | U52: Pagado | W52: =IF(U52="Pagado",1,IF(U52="Solo Cotizado",2,IF(U52="Reservado no Pagado",3,4))) -> 1
R53: Viaje Ricardo-Paty | S53: Extra Bag Hobart Ida | T53: 82 | U53: Pagado | W53: =IF(U53="Pagado",1,IF(U53="Solo Cotizado",2,IF(U53="Reservado no Pagado",3,4))) -> 1
R54: Viaje Ricardo-Paty | S54: Extra Bag Mel Vuelta | T54: 82 | U54: Pagado | W54: =IF(U54="Pagado",1,IF(U54="Solo Cotizado",2,IF(U54="Reservado no Pagado",3,4))) -> 1
R55: Viaje Ricardo-Paty | W55: =IF(U55="Pagado",1,IF(U55="Solo Cotizado",2,IF(U55="Reservado no Pagado",3,4))) -> 4
R58: Otros Fuera Presupuesto
R59: Motivo | S59: Item | T59: Monto | U59: Status | V59: Obs.
S60: Total | T60: =SUM(T61:T75) -> 12249
R61: Viaje Fabiola-HTO-Pauli | S61: Vuelos SLC - BNE | T61: 5511 | U61: Pagado | W61: =IF(U61="Pagado",1,IF(U61="Solo Cotizado",2,IF(U61="Reservado no Pagado",3,4))) -> 1
R62: Viaje Fabiola-HTO-Pauli | S62: Vuelo BNE - Beijing x5 | T62: 3795 | U62: Pagado | W62: =IF(U62="Pagado",1,IF(U62="Solo Cotizado",2,IF(U62="Reservado no Pagado",3,4))) -> 1
R63: Viaje Fabiola-HTO-Pauli | S63: Vuelo BNE - SYDNEY x4 | T63: 1024 | U63: Pagado | W63: =IF(U63="Pagado",1,IF(U63="Solo Cotizado",2,IF(U63="Reservado no Pagado",3,4))) -> 1
R64: Viaje Fabiola-HTO-Pauli | S64: Vuelo BNE-SYDNEY Vale | T64: 256 | U64: Solo Cotizado | W64: =IF(U64="Pagado",1,IF(U64="Solo Cotizado",2,IF(U64="Reservado no Pagado",3,4))) -> 2
R65: Viaje Fabiola-HTO-Pauli | W65: =IF(U65="Pagado",1,IF(U65="Solo Cotizado",2,IF(U65="Reservado no Pagado",3,4))) -> 4
R66: Viaje Fabiola-HTO-Pauli | S66: Hotel Beijing x5 | T66: 524 | U66: Reservado no Pagado | W66: =IF(U66="Pagado",1,IF(U66="Solo Cotizado",2,IF(U66="Reservado no Pagado",3,4))) -> 3
R67: Viaje Fabiola-HTO-Pauli | S67: Hotel Sydney x5 | T67: 1139 | U67: Reservado no Pagado | W67: =IF(U67="Pagado",1,IF(U67="Solo Cotizado",2,IF(U67="Reservado no Pagado",3,4))) -> 3
R68: Viaje Fabiola-HTO-Pauli | W68: =IF(U68="Pagado",1,IF(U68="Solo Cotizado",2,IF(U68="Reservado no Pagado",3,4))) -> 4
R69: Viaje Fabiola-HTO-Pauli | S69: Reserva Opera House | W69: =IF(U69="Pagado",1,IF(U69="Solo Cotizado",2,IF(U69="Reservado no Pagado",3,4))) -> 4
R70: Viaje Fabiola-HTO-Pauli | S70: Reserva AOS | W70: =IF(U70="Pagado",1,IF(U70="Solo Cotizado",2,IF(U70="Reservado no Pagado",3,4))) -> 4
R71: Viaje Fabiola-HTO-Pauli | S71: Reserva QPAC | W71: =IF(U71="Pagado",1,IF(U71="Solo Cotizado",2,IF(U71="Reservado no Pagado",3,4))) -> 4
R72: Viaje Fabiola-HTO-Pauli | W72: =IF(U72="Pagado",1,IF(U72="Solo Cotizado",2,IF(U72="Reservado no Pagado",3,4))) -> 4
R73: Viaje Fabiola-HTO-Pauli | W73: =IF(U73="Pagado",1,IF(U73="Solo Cotizado",2,IF(U73="Reservado no Pagado",3,4))) -> 4
R74: Viaje Fabiola-HTO-Pauli | W74: =IF(U74="Pagado",1,IF(U74="Solo Cotizado",2,IF(U74="Reservado no Pagado",3,4))) -> 4
R75: Viaje Fabiola-HTO-Pauli | W75: =IF(U75="Pagado",1,IF(U75="Solo Cotizado",2,IF(U75="Reservado no Pagado",3,4))) -> 4
S77: JB-HIFI Laptops x2 | T77: 2990 | U77: Pagado
S79: Viaje Papis x2 | T79: =SUMIF(U41:U55,U79,T41:T55)+SUMIF(U61:U75,U79,T61:T75) -> 19267 | U79: Pagado
T80: =SUMIF(U41:U55,U80,T41:T55)+SUMIF(U61:U75,U80,T61:T75) -> 1663 | U80: Reservado no Pagado
T81: =SUMIF(U41:U55,U81,T41:T55)+SUMIF(U61:U75,U81,T61:T75) -> 256 | U81: Solo Cotizado
S82: Total | T82: =T79+T80+T81+T77 -> 24176
V84: p/p
T85: 22257 | U85: Pagado | V85: =T85/2 -> 11128.5
T86: =T85-1900 -> 20357 | U86: Pagado sin Viaje Pauli | V86: =T86/2 -> 10178.5
T87: 1919 | U87: Reservas/Cotizado | V87: =T87/2 -> 959.5
S88: Check Total | T88: =T85+T87-T60-T40-T77 -> 0 | V88: 11138
T90: 9000 | U90: Aporte Vale
T91: =T86+T87-T90 -> 13276 | U91: Aporte Pato
T92: =(T86+T87)/2-T90 -> 2138 | U92: Diferencia
S97: Notas: | T97: Día | U97: Clase | V97: Duración Minutos | W97: % Avance | Z97: =concatenate(LEFT(T97,3)," - ",MID(T97,7,2)) -> Día - | AA97: =ROW() -> 97
I98: Modelo | J98: Hrs 2x | K98: Hrs 2x Acum | S98: Semana 26/01 - 01/02 | T98: W01 - Lunes | U98: JS - 40 | V98: 47 | W98: 41 | X98: Total | Z98: =concatenate(LEFT(T98,3)," - ",MID(T98,7,2)) -> W01 - Lu | AA98: =ROW() -> 98
I99: Lu | J99: 2 | K99: =J99 -> 2 | T99: W01 - Lunes | U99: JS - 41 | V99: 30 | W99: 42 | X99: =SUM(V98:V100) -> 127 | Z99: =concatenate(LEFT(T99,3)," - ",MID(T99,7,2)) -> W01 - Lu | AA99: =ROW() -> 99
I100: Ma | J100: 1.5 | K100: 3.5 | S100: 359.9 | T100: W01 - Lunes | U100: JS - 42 | V100: 50 | W100: 42 | X100: =X99/60 -> 2.1166667 | Z100: =concatenate(LEFT(T100,3)," - ",MID(T100,7,2)) -> W01 - Lu | AA100: =ROW() -> 100
I101: Mi | J101: 2 | K101: 5.5 | S101: Horas Total x Semana | Z101: =concatenate(LEFT(T101,3)," - ",MID(T101,7,2)) -> - | AA101: =ROW() -> 101
I102: Ju | J102: 2 | K102: 7.5 | T102: W01 - Lunes | U102: ReactsJS - 00 | V102: 7 | W102: 42 | X102: Total | Z102: =concatenate(LEFT(T102,3)," - ",MID(T102,7,2)) -> W01 - Lu | AA102: =ROW() -> 102
I103: Vi | J103: 2.5 | K103: 10 | S103: 179.95 | T103: W01 - Lunes | U103: ReactsJS - 01 | V103: 15 | W103: 42 | X103: =SUM(V102:V114) -> 141 | Z103: =concatenate(LEFT(T103,3)," - ",MID(T103,7,2)) -> W01 - Lu | AA103: =ROW() -> 103
I104: Sa | J104: 2.5 | K104: 12.5 | S104: Total Horas 2X Speed | T104: W01 - Lunes | U104: ReactsJS - 02 | V104: 12 | W104: 42 | X104: =X103/60 -> 2.35 | Z104: =concatenate(LEFT(T104,3)," - ",MID(T104,7,2)) -> W01 - Lu | AA104: =ROW() -> 104
I105: Do | J105: 2.5 | K105: 15 | T105: W01 - Lunes | U105: ReactsJS - 03 | V105: 7 | W105: 43 | Z105: =concatenate(LEFT(T105,3)," - ",MID(T105,7,2)) -> W01 - Lu | AA105: =ROW() -> 105
I106: Total Semana | J106: =SUM(J99:J105) -> 15 | T106: W01 - Lunes | U106: ReactsJS - 04 | V106: 12 | W106: 43 | Z106: =concatenate(LEFT(T106,3)," - ",MID(T106,7,2)) -> W01 - Lu | AA106: =ROW() -> 106
M107: 31.806667 | N107: 15.903333 | T107: W01 - Lunes | U107: ReactsJS - 05 | V107: 18 | W107: 43 | Z107: =concatenate(LEFT(T107,3)," - ",MID(T107,7,2)) -> W01 - Lu | AA107: =ROW() -> 107
E108: Curso | F108: Item | G108: Horas Pendiente | H108: Horas 2X | J108: Hrs 2x WK Acum | K108: Diff Acum. | L108: Semana | M108: Total Semana | N108: Total Semana 2X | O108: Primera Fila | P108: Ultima Fila | R108: Horas por día | S108: Horas por día 2x | T108: W01 - Lunes | U108: ReactsJS - 06 | V108: 10 | W108: 43 | Z108: =concatenate(LEFT(T108,3)," - ",MID(T108,7,2)) -> W01 - Lu | AA108: =ROW() -> 108
E109: Prework | F109: Introduccion | G109: =X444/60 -> 0.83333333 | H109: 0.41666667 | I109: Lu | J109: =S109 -> 2.2333333 | L109: W01 | M109: 26.95 | N109: 13.475 | O109: =MINIFS($AA$95:$AA$441,$Z$95:$Z$441,CONCATENATE(L$109," - ",Q109)) -> 98 | P109: =MAXIFS($AA$95:$AA$441,$Z$95:$Z$441,CONCATENATE(L$109," - ",Q109)) -> 114 | Q109: Lu | R109: =IF(P109=0,0,SUM(INDIRECT("V"&O109&":V"&P109))/60) -> 4.4666667 | S109: 2.2333333 | T109: W01 - Lunes | U109: ReactsJS - 07 | V109: 25 | W109: 43 | Z109: =concatenate(LEFT(T109,3)," - ",MID(T109,7,2)) -> W01 - Lu | AA109: =ROW() -> 109
F110: Bases de la informatica | G110: =X448/60 -> 2.2833333 | H110: 1.1416667 | I110: Ma | J110: 3.5583333 | O110: =MINIFS($AA$95:$AA$441,$Z$95:$Z$441,CONCATENATE(L$109," - ",Q110)) -> 116 | P110: =MAXIFS($AA$95:$AA$441,$Z$95:$Z$441,CONCATENATE(L$109," - ",Q110)) -> 120 | Q110: Ma | R110: =IF(P110=0,0,SUM(INDIRECT("V"&O110&":V"&P110))/60) -> 2.65 | S110: 1.325 | T110: W01 - Lunes | U110: ReactsJS - 08 | V110: 11 | W110: 43 | Z110: =concatenate(LEFT(T110,3)," - ",MID(T110,7,2)) -> W01 - Lu | AA110: =ROW() -> 110
F111: Pseudocodigo | G111: =X451/60 -> 11.583333 | H111: 5.7916667 | I111: Mi | J111: 5.75 | O111: =MINIFS($AA$95:$AA$441,$Z$95:$Z$441,CONCATENATE(L$109," - ",Q111)) -> 121 | P111: =MAXIFS($AA$95:$AA$441,$Z$95:$Z$441,CONCATENATE(L$109," - ",Q111)) -> 125 | Q111: Mi | R111: =IF(P111=0,0,SUM(INDIRECT("V"&O111&":V"&P111))/60) -> 4.3833333 | S111: 2.1916667 | T111: W01 - Lunes | U111: ReactsJS - 09 | V111: 10 | W111: 43 | Z111: =concatenate(LEFT(T111,3)," - ",MID(T111,7,2)) -> W01 - Lu | AA111: =ROW() -> 111
F112: Linux y Terminal | G112: =X468/60 -> 13.133333 | H112: 6.5666667 | I112: Ju | J112: 8 | O112: =MINIFS($AA$95:$AA$441,$Z$95:$Z$441,CONCATENATE(L$109," - ",Q112)) -> 126 | P112: =MAXIFS($AA$95:$AA$441,$Z$95:$Z$441,CONCATENATE(L$109," - ",Q112)) -> 132 | Q112: Ju | R112: =IF(P112=0,0,SUM(INDIRECT("V"&O112&":V"&P112))/60) -> 4.5 | S112: 2.25 | T112: W01 - Lunes | U112: ReactsJS - 10 | V112: 3 | W112: 43 | Z112: =concatenate(LEFT(T112,3)," - ",MID(T112,7,2)) -> W01 - Lu | AA112: =ROW() -> 112
...

Sheet Presupuesto
C2: Weeks/Year | D2: 52 | F2: CLP/AUD | G2: 600
C3: Weeks/Month | D3: 4.3
A5: Costos Fijos | D5: Week | E5: Month | F5: Year | H5: Dias Mes | I5: Clasificacion | J5: SubClasificacion | K5: Presupuesto Mensual | L5: Dia
C6: Depto | D6: 725 | E6: =D6*$D$3 -> 3117.5 | F6: =E6*12 -> 37410 | H6: =Graficos!A1 -> 31 | I6: Costo Fijo - Depto | J6: Depto | K6: =E6 -> 3117.5 | L6: =K6/$H$6 -> 100.56452 | N6: Mensual
C7: Luz | D7: =E7/$D$3 -> 42.627907 | E7: 183.3 | F7: =E7*12 -> 2199.6 | I7: Costo Fijo - Depto | J7: Luz | K7: =E7 -> 183.3 | L7: =K7/$H$6 -> 5.9129032 | N7: Trimestral
C8: Internet | D8: =E8/$D$3 -> 20.465116 | E8: 88 | F8: =E8*12 -> 1056 | I8: Costo Fijo - Depto | J8: Internet | K8: =E8 -> 88 | L8: =K8/$H$6 -> 2.8387097 | N8: Mensual
I9: Costo Fijo - Otros | J9: Bupa | K9: =E12 -> 230 | L9: =K9/$H$6 -> 7.4193548 | N9: Mensual
B10: SubTotal | C10: Depto | D10: =SUM(D6:D9) -> 788.09302 | E10: =SUM(E6:E9) -> 3388.8 | F10: =SUM(F6:F9) -> 40665.6 | I10: Costo Fijo - Otros | J10: Telstra | K10: =E13 -> 140 | L10: =K10/$H$6 -> 4.516129 | N10: Mensual
I11: Costo Variable - Comidas | J11: Desayuno | K11: =E20 -> 129 | L11: =K11/$H$6 -> 4.1612903 | M11: =SUMIFS(Data!$B$2:$B$80,Data!$D$2:$D$80,$J$6:$J$32) -> 156 | N11: Mensual
C12: Bupa | D12: =E12/$D$3 -> 53.488372 | E12: 230 | F12: =E12*12 -> 2760 | I12: Costo Variable - Comidas | J12: Almuerzo | K12: =E21 -> 344 | L12: =K12/$H$6 -> 11.096774 | M12: =SUMIFS(Data!$B$2:$B$80,Data!$D$2:$D$80,$J$6:$J$32) -> 281 | N12: Mensual
C13: Telstra | D13: =E13/$D$3 -> 32.55814 | E13: 140 | F13: =E13*12 -> 1680 | I13: Costo Variable - Comidas | J13: Cena | K13: =E22 -> 215 | L13: =K13/$H$6 -> 6.9354839 | M13: =SUMIFS(Data!$B$2:$B$80,Data!$D$2:$D$80,$J$6:$J$32) -> 190 | N13: Mensual
I14: Costo Variable - Comidas | J14: Super | K14: =E26 -> 645 | L14: =K14/$H$6 -> 20.806452 | M14: =SUMIFS(Data!$B$2:$B$80,Data!$D$2:$D$80,$J$6:$J$32) -> 866 | N14: Mensual
B15: SubTotal | C15: Costos Fijos | D15: =SUM(D12:D14) -> 86.046512 | E15: =SUM(E12:E14) -> 370 | F15: =SUM(F12:F14) -> 4440 | I15: Costo Variable - Otros | J15: Otros Casa | K15: =E25 -> 215 | L15: =K15/$H$6 -> 6.9354839 | M15: =SUMIFS(Data!$B$2:$B$80,Data!$D$2:$D$80,$J$6:$J$32) -> 0 | N15: Mensual
I16: Costo Variable - Otros | J16: Corte Pelo - Salud - Remedios | K16: =E29 -> 100 | L16: =K16/$H$6 -> 3.2258065 | M16: =SUMIFS(Data!$B$2:$B$80,Data!$D$2:$D$80,$J$6:$J$32) -> 112 | N16: Mensual
B17: SubTotal Fijos | C17: Costos Fijos | D17: =D15+D10 -> 874.13953 | E17: =E15+E10 -> 3758.8 | F17: =F15+F10 -> 45105.6 | I17: Costo Variable - Otros | J17: Otros | K17: =E24 -> 172 | L17: =K17/$H$6 -> 5.5483871 | M17: =SUMIFS(Data!$B$2:$B$80,Data!$D$2:$D$80,$J$6:$J$32) -> 0 | N17: Mensual
A18: Costos Variables | I18: Costo Variable - Transporte | J18: Transporte - Scooter | K18: =E30 -> 50 | L18: =K18/$H$6 -> 1.6129032 | M18: =SUMIFS(Data!$B$2:$B$80,Data!$D$2:$D$80,$J$6:$J$32) -> 20 | N18: Mensual
I19: Costo Variable - Transporte | J19: Uber | K19: =E31 -> 120 | L19: =K19/$H$6 -> 3.8709677 | M19: =SUMIFS(Data!$B$2:$B$80,Data!$D$2:$D$80,$J$6:$J$32) -> 0 | N19: Mensual
B20: Comidas | C20: Desayuno | D20: 30 | E20: =D20*$D$3 -> 129 | F20: =E20*12 -> 1548 | I20: Costo Variable - Auto | J20: Bencina | K20: =E36 -> 80 | L20: =K20/$H$6 -> 2.5806452 | M20: =SUMIFS(Data!$B$2:$B$80,Data!$D$2:$D$80,$J$6:$J$32) -> 46 | N20: Mensual
C21: Almuerzo | D21: 80 | E21: =D21*$D$3 -> 344 | F21: =E21*12 -> 4128 | I21: Costo Variable - Auto | J21: Seguro | K21: =E37 -> 100 | L21: =K21/$H$6 -> 3.2258065 | M21: =SUMIFS(Data!$B$2:$B$80,Data!$D$2:$D$80,$J$6:$J$32) -> 0 | N21: Mensual
C22: Cena | D22: 50 | E22: =D22*$D$3 -> 215 | F22: =E22*12 -> 2580 | I22: Costo Variable - Auto | J22: Estacionamiento - CarWash | K22: =E38 -> 35 | L22: =K22/$H$6 -> 1.1290323 | M22: =SUMIFS(Data!$B$2:$B$80,Data!$D$2:$D$80,$J$6:$J$32) -> 22 | N22: Mensual
I23: Costo Variable - Auto | J23: Mecanico | K23: =E39 -> 50 | L23: =K23/$H$6 -> 1.6129032 | M23: =SUMIFS(Data!$B$2:$B$80,Data!$D$2:$D$80,$J$6:$J$32) -> 0 | N23: Anual
C24: Otros | D24: 40 | E24: =D24*$D$3 -> 172 | F24: =E24*12 -> 2064 | I24: Costo Variable - Auto | J24: REGO | K24: =E40 -> 75 | L24: =K24/$H$6 -> 2.4193548 | M24: =SUMIFS(Data!$B$2:$B$80,Data!$D$2:$D$80,$J$6:$J$32) -> 0 | N24: Semestral
C25: Otros Casa | D25: 50 | E25: =D25*$D$3 -> 215 | F25: =E25*12 -> 2580 | I25: Costo Variable - Auto | J25: Peajes | K25: =E41 -> 40 | L25: =K25/$H$6 -> 1.2903226 | M25: =SUMIFS(Data!$B$2:$B$80,Data!$D$2:$D$80,$J$6:$J$32) -> 42 | N25: Mensual
C26: Super | D26: 150 | E26: =D26*$D$3 -> 645 | F26: =E26*12 -> 7740 | I26: Costo Variable - Gasto Pega | J26: Uber Pega | K26: =E44 -> 236.5 | L26: =K26/$H$6 -> 7.6290323 | M26: =SUMIFS(Data!$B$2:$B$80,Data!$D$2:$D$80,$J$6:$J$32) -> 202 | N26: Mensual
B27: SubTotal | C27: Comida + Super | D27: =SUM(D20:D26) -> 400 | E27: =SUM(E20:E26) -> 1720 | F27: =SUM(F20:F26) -> 20640 | I27: Costo Variable - Gasto Pega | J27: Tren - GoCard - Scooter Pega | K27: =E45 -> 98.9 | L27: =K27/$H$6 -> 3.1903226 | M27: =SUMIFS(Data!$B$2:$B$80,Data!$D$2:$D$80,$J$6:$J$32) -> 89 | N27: Mensual
I28: Costo Variable - Gasto Pega | J28: Parking - Otros Pega | K28: =E46 -> 120.4 | L28: =K28/$H$6 -> 3.883871 | M28: =SUMIFS(Data!$B$2:$B$80,Data!$D$2:$D$80,$J$6:$J$32) -> 0 | N28: Mensual
C29: Corte Pelo | D29: =E29/$D$3 -> 23.255814 | E29: 100 | F29: =E29*12 -> 1200 | I29: Costo Variable - Personales | J29: Otros Personales | K29: =E50 -> 150 | L29: =K29/$H$6 -> 4.8387097 | M29: =SUMIFS(Data!$B$2:$B$80,Data!$D$2:$D$80,$J$6:$J$32) -> 388.67 | N29: Mensual
C30: Transporte | D30: =E30/$D$3 -> 11.627907 | E30: 50 | F30: =E30*12 -> 600 | I30: Costo Variable - Personales | J30: Libros - Cursos | K30: =E51 -> 129 | L30: =K30/$H$6 -> 4.1612903 | M30: =SUMIFS(Data!$B$2:$B$80,Data!$D$2:$D$80,$J$6:$J$32) -> 0 | N30: Mensual
C31: Uber | D31: =E31/$D$3 -> 27.906977 | E31: 120 | F31: =E31*12 -> 1440 | I31: Costo Variable - Personales | J31: Ropa - Accesorios | K31: =E52 -> 86 | L31: =K31/$H$6 -> 2.7741935 | M31: =SUMIFS(Data!$B$2:$B$80,Data!$D$2:$D$80,$J$6:$J$32) -> 178 | N31: Mensual
I32: Costo Variable - Personales | J32: Regalos - Eventos | K32: =E53 | L32: =K32/$H$6 -> 0 | M32: =SUMIFS(Data!$B$2:$B$80,Data!$D$2:$D$80,$J$6:$J$32) -> 91 | N32: Mensual
I33: Costo Variable - Personales | J33: Viajes | K33: =E54 -> 250 | L33: =K33/$H$6 -> 8.0645161 | M33: =SUMIFS(Data!$B$2:$B$80,Data!$D$2:$D$80,$J$6:$J$32) -> 0 | N33: Anual
B34: SubTotal | C34: Otros | D34: =sum(D29:D33) -> 62.790698 | E34: =sum(E29:E33) -> 270 | F34: =sum(F29:F33) -> 3240 | J34: Otros Fuera Presupuesto
C36: Bencina | D36: =E36/$D$3 -> 18.604651 | E36: 80 | F36: =E36*12 -> 960 | I36: Presupuesto Total x Mes | K36: =SUM(K6:K33) -> 7199.6
C37: Seguro Auto | D37: =E37/$D$3 -> 23.255814 | E37: 100 | F37: =E37*12 -> 1200 | I37: Presupuesto - Variable | K37: =SUM(K25:K31,K11:K22,K8) -> 3153.8
C38: Estacionamiento | D38: =E38/$D$3 -> 8.1395349 | E38: 35 | F38: =E38*12 -> 420
C39: Mecanico | D39: =E39/$D$3 -> 11.627907 | E39: =F39/12 -> 50 | F39: 600
C40: REGO | D40: =E40/$D$3 -> 17.44186 | E40: =F40/12 -> 75 | F40: 900
C41: Peajes/Linkt | D41: =E41/$D$3 -> 9.3023256 | E41: 40 | F41: =E41*12 -> 480
B42: SubTotal | C42: Auto | D42: =sum(D36:D41) -> 88.372093 | E42: =sum(E36:E41) -> 380 | F42: =sum(F36:F41) -> 4560
B44: Trabajo | C44: Uber a Pega | D44: 55 | E44: =D44*$D$3 -> 236.5 | F44: =E44*12 -> 2838
C45: Tren + Transporte | D45: 23 | E45: =D45*$D$3 -> 98.9 | F45: =E45*12 -> 1186.8
C46: Parking | D46: 28 | E46: =D46*$D$3 -> 120.4 | F46: =E46*12 -> 1444.8
B48: SubTotal | C48: Trabajo | D48: =sum(D44:D47) -> 106 | E48: =sum(E44:E47) -> 455.8 | F48: =sum(F44:F47) -> 5469.6
B50: Personales | C50: Otros Personales | D50: =E50/$D$3 -> 34.883721 | E50: 150 | F50: =E50*12 -> 1800
C51: Libros - Cursos | D51: 30 | E51: =D51*$D$3 -> 129 | F51: =E51*12 -> 1548
C52: Ropa | D52: 20 | E52: =D52*$D$3 -> 86 | F52: =E52*12 -> 1032
C53: Regalos
C54: Viajes | D54: =E54/$D$3 -> 58.139535 | E54: =F54/12 -> 250 | F54: 3000
B55: SubTotal | C55: Personales | D55: =sum(D50:D54) -> 143.02326 | E55: =sum(E50:E54) -> 615 | F55: =sum(F50:F54) -> 7380
C57: Total | D57: =D55+D48+D42+D34+D27+D17 -> 1674.3256 | E57: =E55+E48+E42+E34+E27+E17 -> 7199.6 | F57: =F55+F48+F42+F34+F27+F17 -> 86395.2
C58: CLP | D58: =D57*$G$2 -> 1004595.3 | E58: =E57*$G$2 -> 4319760 | F58: =F57*$G$2 -> 51837120
B61: CLP | C61: Costos Chile | D61: 576923 | E61: 2500000 | F61: 30000000
B62: AUD | C62: Costos Chile | D62: =D61/$G$2 -> 961.53833 | E62: =E61/$G$2 -> 4166.6667 | F62: =F61/$G$2 -> 50000
C64: Total AUD | D64: =D62+D57 -> 2635.8639 | E64: =E62+E57 -> 11366.267 | F64: =F62+F57 -> 136395.2
B65: CLP | D65: =D64*$G$2 -> 1581518.3 | E65: =E64*$G$2 -> 6819760 | F65: =F64*$G$2 -> 81837120
C67: Savings
C68: Income | D68: =E68/$D$3 -> 2500 | E68: 10750 | F68: =E68*12 -> 129000
C69: Total | D69: =D68+D67 -> 2500 | E69: =E68+E67 -> 10750 | F69: =F68+F67 -> 129000
B70: CLP | D70: =D69*$G$2 -> 1500000 | E70: =E69*$G$2 -> 6450000 | F70: =F69*$G$2 -> 77400000
C71: Dif | D71: =D69-D64 -> -135.86391 | E71: =E69-E64 -> -616.26667 | F71: =F69-F64 -> -7395.2
B72: CLP | D72: =D71*$G$2 -> -81518.349 | E72: =E71*$G$2 -> -369760 | F72: =F71*$G$2 -> -4437120

Sheet Acumulado
C2: Dia | D2: 1 | E2: =D2+1 -> 2 | F2: =E2+1 -> 3 | G2: =F2+1 -> 4 | H2: =G2+1 -> 5 | I2: =H2+1 -> 6 | J2: =I2+1 -> 7 | K2: =J2+1 -> 8 | L2: =K2+1 -> 9 | ... AH2: =AG2+1 -> 31 | AI2: Total Mes
A3: Real | B3: Clasificacion | C3: SubClasificacion
B4: Costo Fijo - Depto | C4: Luz | D4: =SUMIFS(Data!$B$2:$B$100,Data!$A$2:$A$100,D$2,Data!$D$2:$D$100,$C4) -> 0 | E4: =SUMIFS(Data!$B$2:$B$100,Data!$A$2:$A$100,E$2,Data!$D$2:$D$100,$C4) -> 0 | F4: =SUMIFS(Data!$B$2:$B$100,Data!$A$2:$A$100,F$2,Data!$D$2:$D$100,$C4) -> 0 | G4: =SUMIFS(Data!$B$2:$B$100,Data!$A$2:$A$100,G$2,Data!$D$2:$D$100,$C4) -> 0 | H4: =SUMIFS(Data!$B$2:$B$100,Data!$A$2:$A$100,H$2,Data!$D$2:$D$100,$C4) -> 0 | I4: =SUMIFS(Data!$B$2:$B$100,Data!$A$2:$A$100,I$2,Data!$D$2:$D$100,$C4) -> 0 | J4: =SUMIFS(Data!$B$2:$B$100,Data!$A$2:$A$100,J$2,Data!$D$2:$D$100,$C4) -> 0 | K4: =SUMIFS(Data!$B$2:$B$100,Data!$A$2:$A$100,K$2,Data!$D$2:$D$100,$C4) -> 0 | ... AH4: =SUMIFS(Data!$B$2:$B$100,Data!$A$2:$A$100,AH$2,Data!$D$2:$D$100,$C4) -> 0 | AI4: =SUM(D4:AH4) -> 0
B5: Costo Fijo - Depto | C5: Internet | D5: =SUMIFS(Data!$B$2:$B$100,Data!$A$2:$A$100,D$2,Data!$D$2:$D$100,$C5) -> 95 | E5: =SUMIFS(Data!$B$2:$B$100,Data!$A$2:$A$100,E$2,Data!$D$2:$D$100,$C5) -> 0 | F5: =SUMIFS(Data!$B$2:$B$100,Data!$A$2:$A$100,F$2,Data!$D$2:$D$100,$C5) -> 0 | G5: =SUMIFS(Data!$B$2:$B$100,Data!$A$2:$A$100,G$2,Data!$D$2:$D$100,$C5) -> 0 | H5: =SUMIFS(Data!$B$2:$B$100,Data!$A$2:$A$100,H$2,Data!$D$2:$D$100,$C5) -> 0 | I5: =SUMIFS(Data!$B$2:$B$100,Data!$A$2:$A$100,I$2,Data!$D$2:$D$100,$C5) -> 0 | J5: =SUMIFS(Data!$B$2:$B$100,Data!$A$2:$A$100,J$2,Data!$D$2:$D$100,$C5) -> 0 | K5: =SUMIFS(Data!$B$2:$B$100,Data!$A$2:$A$100,K$2,Data!$D$2:$D$100,$C5) -> 0 | ... AH5: =SUMIFS(Data!$B$2:$B$100,Data!$A$2:$A$100,AH$2,Data!$D$2:$D$100,$C5) -> 0 | AI5: =SUM(D5:AH5) -> 95
B6: Costo Variable - Comidas | C6: Desayuno | D6: =SUMIFS(Data!$B$2:$B$100,Data!$A$2:$A$100,D$2,Data!$D$2:$D$100,$C6) -> 11 | E6: =SUMIFS(Data!$B$2:$B$100,Data!$A$2:$A$100,E$2,Data!$D$2:$D$100,$C6) -> 0 | F6: =SUMIFS(Data!$B$2:$B$100,Data!$A$2:$A$100,F$2,Data!$D$2:$D$100,$C6) -> 22 | G6: =SUMIFS(Data!$B$2:$B$100,Data!$A$2:$A$100,G$2,Data!$D$2:$D$100,$C6) -> 0 | H6: =SUMIFS(Data!$B$2:$B$100,Data!$A$2:$A$100,H$2,Data!$D$2:$D$100,$C6) -> 0 | I6: =SUMIFS(Data!$B$2:$B$100,Data!$A$2:$A$100,I$2,Data!$D$2:$D$100,$C6) -> 0 | J6: =SUMIFS(Data!$B$2:$B$100,Data!$A$2:$A$100,J$2,Data!$D$2:$D$100,$C6) -> 0 | K6: =SUMIFS(Data!$B$2:$B$100,Data!$A$2:$A$100,K$2,Data!$D$2:$D$100,$C6) -> 0 | ... AH6: =SUMIFS(Data!$B$2:$B$100,Data!$A$2:$A$100,AH$2,Data!$D$2:$D$100,$C6) -> 0 | AI6: =SUM(D6:AH6) -> 156
B7: Costo Variable - Comidas | C7: Almuerzo | D7: =SUMIFS(Data!$B$2:$B$100,Data!$A$2:$A$100,D$2,Data!$D$2:$D$100,$C7) -> 0 | E7: =SUMIFS(Data!$B$2:$B$100,Data!$A$2:$A$100,E$2,Data!$D$2:$D$100,$C7) -> 39 | F7: =SUMIFS(Data!$B$2:$B$100,Data!$A$2:$A$100,F$2,Data!$D$2:$D$100,$C7) -> 0 | G7: =SUMIFS(Data!$B$2:$B$100,Data!$A$2:$A$100,G$2,Data!$D$2:$D$100,$C7) -> 85 | H7: =SUMIFS(Data!$B$2:$B$100,Data!$A$2:$A$100,H$2,Data!$D$2:$D$100,$C7) -> 0 | I7: =SUMIFS(Data!$B$2:$B$100,Data!$A$2:$A$100,I$2,Data!$D$2:$D$100,$C7) -> 0 | J7: =SUMIFS(Data!$B$2:$B$100,Data!$A$2:$A$100,J$2,Data!$D$2:$D$100,$C7) -> 0 | K7: =SUMIFS(Data!$B$2:$B$100,Data!$A$2:$A$100,K$2,Data!$D$2:$D$100,$C7) -> 0 | ... AH7: =SUMIFS(Data!$B$2:$B$100,Data!$A$2:$A$100,AH$2,Data!$D$2:$D$100,$C7) -> 0 | AI7: =SUM(D7:AH7) -> 281
B8: Costo Variable - Comidas | C8: Cena | D8: =SUMIFS(Data!$B$2:$B$100,Data!$A$2:$A$100,D$2,Data!$D$2:$D$100,$C8) -> 0 | E8: =SUMIFS(Data!$B$2:$B$100,Data!$A$2:$A$100,E$2,Data!$D$2:$D$100,$C8) -> 0 | F8: =SUMIFS(Data!$B$2:$B$100,Data!$A$2:$A$100,F$2,Data!$D$2:$D$100,$C8) -> 0 | G8: =SUMIFS(Data!$B$2:$B$100,Data!$A$2:$A$100,G$2,Data!$D$2:$D$100,$C8) -> 0 | H8: =SUMIFS(Data!$B$2:$B$100,Data!$A$2:$A$100,H$2,Data!$D$2:$D$100,$C8) -> 24 | I8: =SUMIFS(Data!$B$2:$B$100,Data!$A$2:$A$100,I$2,Data!$D$2:$D$100,$C8) -> 0 | J8: =SUMIFS(Data!$B$2:$B$100,Data!$A$2:$A$100,J$2,Data!$D$2:$D$100,$C8) -> 16 | K8: =SUMIFS(Data!$B$2:$B$100,Data!$A$2:$A$100,K$2,Data!$D$2:$D$100,$C8) -> 0 | ... AH8: =SUMIFS(Data!$B$2:$B$100,Data!$A$2:$A$100,AH$2,Data!$D$2:$D$100,$C8) -> 0 | AI8: =SUM(D8:AH8) -> 190
B9: Costo Variable - Comidas | C9: Super | D9: =SUMIFS(Data!$B$2:$B$100,Data!$A$2:$A$100,D$2,Data!$D$2:$D$100,$C9) -> 0 | E9: =SUMIFS(Data!$B$2:$B$100,Data!$A$2:$A$100,E$2,Data!$D$2:$D$100,$C9) -> 110 | F9: =SUMIFS(Data!$B$2:$B$100,Data!$A$2:$A$100,F$2,Data!$D$2:$D$100,$C9) -> 0 | G9: =SUMIFS(Data!$B$2:$B$100,Data!$A$2:$A$100,G$2,Data!$D$2:$D$100,$C9) -> 0 | H9: =SUMIFS(Data!$B$2:$B$100,Data!$A$2:$A$100,H$2,Data!$D$2:$D$100,$C9) -> 0 | I9: =SUMIFS(Data!$B$2:$B$100,Data!$A$2:$A$100,I$2,Data!$D$2:$D$100,$C9) -> 0 | J9: =SUMIFS(Data!$B$2:$B$100,Data!$A$2:$A$100,J$2,Data!$D$2:$D$100,$C9) -> 0 | K9: =SUMIFS(Data!$B$2:$B$100,Data!$A$2:$A$100,K$2,Data!$D$2:$D$100,$C9) -> 10 | ... AH9: =SUMIFS(Data!$B$2:$B$100,Data!$A$2:$A$100,AH$2,Data!$D$2:$D$100,$C9) -> 0 | AI9: =SUM(D9:AH9) -> 866
B10: Costo Variable - Otros | C10: Otros Casa | D10: =SUMIFS(Data!$B$2:$B$100,Data!$A$2:$A$100,D$2,Data!$D$2:$D$100,$C10) -> 0 | E10: =SUMIFS(Data!$B$2:$B$100,Data!$A$2:$A$100,E$2,Data!$D$2:$D$100,$C10) -> 0 | F10: =SUMIFS(Data!$B$2:$B$100,Data!$A$2:$A$100,F$2,Data!$D$2:$D$100,$C10) -> 0 | G10: =SUMIFS(Data!$B$2:$B$100,Data!$A$2:$A$100,G$2,Data!$D$2:$D$100,$C10) -> 0 | H10: =SUMIFS(Data!$B$2:$B$100,Data!$A$2:$A$100,H$2,Data!$D$2:$D$100,$C10) -> 0 | I10: =SUMIFS(Data!$B$2:$B$100,Data!$A$2:$A$100,I$2,Data!$D$2:$D$100,$C10) -> 0 | J10: =SUMIFS(Data!$B$2:$B$100,Data!$A$2:$A$100,J$2,Data!$D$2:$D$100,$C10) -> 0 | K10: =SUMIFS(Data!$B$2:$B$100,Data!$A$2:$A$100,K$2,Data!$D$2:$D$100,$C10) -> 0 | ... AH10: =SUMIFS(Data!$B$2:$B$100,Data!$A$2:$A$100,AH$2,Data!$D$2:$D$100,$C10) -> 0 | AI10: =SUM(D10:AH10) -> 0
B11: Costo Variable - Otros | C11: Corte Pelo - Salud - Remedios | D11: =SUMIFS(Data!$B$2:$B$100,Data!$A$2:$A$100,D$2,Data!$D$2:$D$100,$C11) -> 0 | E11: =SUMIFS(Data!$B$2:$B$100,Data!$A$2:$A$100,E$2,Data!$D$2:$D$100,$C11) -> 0 | F11: =SUMIFS(Data!$B$2:$B$100,Data!$A$2:$A$100,F$2,Data!$D$2:$D$100,$C11) -> 0 | G11: =SUMIFS(Data!$B$2:$B$100,Data!$A$2:$A$100,G$2,Data!$D$2:$D$100,$C11) -> 0 | H11: =SUMIFS(Data!$B$2:$B$100,Data!$A$2:$A$100,H$2,Data!$D$2:$D$100,$C11) -> 0 | I11: =SUMIFS(Data!$B$2:$B$100,Data!$A$2:$A$100,I$2,Data!$D$2:$D$100,$C11) -> 0 | J11: =SUMIFS(Data!$B$2:$B$100,Data!$A$2:$A$100,J$2,Data!$D$2:$D$100,$C11) -> 0 | K11: =SUMIFS(Data!$B$2:$B$100,Data!$A$2:$A$100,K$2,Data!$D$2:$D$100,$C11) -> 56 | ... AH11: =SUMIFS(Data!$B$2:$B$100,Data!$A$2:$A$100,AH$2,Data!$D$2:$D$100,$C11) -> 0 | AI11: =SUM(D11:AH11) -> 112
B12: Costo Variable - Otros | C12: Otros | D12: =SUMIFS(Data!$B$2:$B$100,Data!$A$2:$A$100,D$2,Data!$D$2:$D$100,$C12) -> 0 | E12: =SUMIFS(Data!$B$2:$B$100,Data!$A$2:$A$100,E$2,Data!$D$2:$D$100,$C12) -> 0 | F12: =SUMIFS(Data!$B$2:$B$100,Data!$A$2:$A$100,F$2,Data!$D$2:$D$100,$C12) -> 0 | G12: =SUMIFS(Data!$B$2:$B$100,Data!$A$2:$A$100,G$2,Data!$D$2:$D$100,$C12) -> 0 | H12: =SUMIFS(Data!$B$2:$B$100,Data!$A$2:$A$100,H$2,Data!$D$2:$D$100,$C12) -> 0 | I12: =SUMIFS(Data!$B$2:$B$100,Data!$A$2:$A$100,I$2,Data!$D$2:$D$100,$C12) -> 0 | J12: =SUMIFS(Data!$B$2:$B$100,Data!$A$2:$A$100,J$2,Data!$D$2:$D$100,$C12) -> 0 | K12: =SUMIFS(Data!$B$2:$B$100,Data!$A$2:$A$100,K$2,Data!$D$2:$D$100,$C12) -> 0 | ... AH12: =SUMIFS(Data!$B$2:$B$100,Data!$A$2:$A$100,AH$2,Data!$D$2:$D$100,$C12) -> 0 | AI12: =SUM(D12:AH12) -> 0
B13: Costo Variable - Transporte | C13: Transporte - Scooter | D13: =SUMIFS(Data!$B$2:$B$100,Data!$A$2:$A$100,D$2,Data!$D$2:$D$100,$C13) -> 0 | E13: =SUMIFS(Data!$B$2:$B$100,Data!$A$2:$A$100,E$2,Data!$D$2:$D$100,$C13) -> 0 | F13: =SUMIFS(Data!$B$2:$B$100,Data!$A$2:$A$100,F$2,Data!$D$2:$D$100,$C13) -> 0 | G13: =SUMIFS(Data!$B$2:$B$100,Data!$A$2:$A$100,G$2,Data!$D$2:$D$100,$C13) -> 0 | H13: =SUMIFS(Data!$B$2:$B$100,Data!$A$2:$A$100,H$2,Data!$D$2:$D$100,$C13) -> 0 | I13: =SUMIFS(Data!$B$2:$B$100,Data!$A$2:$A$100,I$2,Data!$D$2:$D$100,$C13) -> 0 | J13: =SUMIFS(Data!$B$2:$B$100,Data!$A$2:$A$100,J$2,Data!$D$2:$D$100,$C13) -> 3 | K13: =SUMIFS(Data!$B$2:$B$100,Data!$A$2:$A$100,K$2,Data!$D$2:$D$100,$C13) -> 6 | ... AH13: =SUMIFS(Data!$B$2:$B$100,Data!$A$2:$A$100,AH$2,Data!$D$2:$D$100,$C13) -> 0 | AI13: =SUM(D13:AH13) -> 20
B14: Costo Variable - Transporte | C14: Uber | D14: =SUMIFS(Data!$B$2:$B$100,Data!$A$2:$A$100,D$2,Data!$D$2:$D$100,$C14) -> 0 | E14: =SUMIFS(Data!$B$2:$B$100,Data!$A$2:$A$100,E$2,Data!$D$2:$D$100,$C14) -> 0 | F14: =SUMIFS(Data!$B$2:$B$100,Data!$A$2:$A$100,F$2,Data!$D$2:$D$100,$C14) -> 0 | G14: =SUMIFS(Data!$B$2:$B$100,Data!$A$2:$A$100,G$2,Data!$D$2:$D$100,$C14) -> 0 | H14: =SUMIFS(Data!$B$2:$B$100,Data!$A$2:$A$100,H$2,Data!$D$2:$D$100,$C14) -> 0 | I14: =SUMIFS(Data!$B$2:$B$100,Data!$A$2:$A$100,I$2,Data!$D$2:$D$100,$C14) -> 0 | J14: =SUMIFS(Data!$B$2:$B$100,Data!$A$2:$A$100,J$2,Data!$D$2:$D$100,$C14) -> 0 | K14: =SUMIFS(Data!$B$2:$B$100,Data!$A$2:$A$100,K$2,Data!$D$2:$D$100,$C14) -> 0 | ... AH14: =SUMIFS(Data!$B$2:$B$100,Data!$A$2:$A$100,AH$2,Data!$D$2:$D$100,$C14) -> 0 | AI14: =SUM(D14:AH14) -> 0
B15: Costo Variable - Auto | C15: Bencina | D15: =SUMIFS(Data!$B$2:$B$100,Data!$A$2:$A$100,D$2,Data!$D$2:$D$100,$C15) -> 0 | E15: =SUMIFS(Data!$B$2:$B$100,Data!$A$2:$A$100,E$2,Data!$D$2:$D$100,$C15) -> 0 | F15: =SUMIFS(Data!$B$2:$B$100,Data!$A$2:$A$100,F$2,Data!$D$2:$D$100,$C15) -> 0 | G15: =SUMIFS(Data!$B$2:$B$100,Data!$A$2:$A$100,G$2,Data!$D$2:$D$100,$C15) -> 0 | H15: =SUMIFS(Data!$B$2:$B$100,Data!$A$2:$A$100,H$2,Data!$D$2:$D$100,$C15) -> 0 | I15: =SUMIFS(Data!$B$2:$B$100,Data!$A$2:$A$100,I$2,Data!$D$2:$D$100,$C15) -> 0 | J15: =SUMIFS(Data!$B$2:$B$100,Data!$A$2:$A$100,J$2,Data!$D$2:$D$100,$C15) -> 0 | K15: =SUMIFS(Data!$B$2:$B$100,Data!$A$2:$A$100,K$2,Data!$D$2:$D$100,$C15) -> 0 | ... AH15: =SUMIFS(Data!$B$2:$B$100,Data!$A$2:$A$100,AH$2,Data!$D$2:$D$100,$C15) -> 0 | AI15: =SUM(D15:AH15) -> 46
... B27: Costo Variable - Personales | C27: Regalos - Eventos | D27: =SUMIFS(Data!$B$2:$B$100,Data!$A$2:$A$100,D$2,Data!$D$2:$D$100,$C27) -> 0 | E27: =SUMIFS(Data!$B$2:$B$100,Data!$A$2:$A$100,E$2,Data!$D$2:$D$100,$C27) -> 50 | F27: =SUMIFS(Data!$B$2:$B$100,Data!$A$2:$A$100,F$2,Data!$D$2:$D$100,$C27) -> 0 | G27: =SUMIFS(Data!$B$2:$B$100,Data!$A$2:$A$100,G$2,Data!$D$2:$D$100,$C27) -> 0 | H27: =SUMIFS(Data!$B$2:$B$100,Data!$A$2:$A$100,H$2,Data!$D$2:$D$100,$C27) -> 0 | I27: =SUMIFS(Data!$B$2:$B$100,Data!$A$2:$A$100,I$2,Data!$D$2:$D$100,$C27) -> 0 | J27: =SUMIFS(Data!$B$2:$B$100,Data!$A$2:$A$100,J$2,Data!$D$2:$D$100,$C27) -> 0 | K27: =SUMIFS(Data!$B$2:$B$100,Data!$A$2:$A$100,K$2,Data!$D$2:$D$100,$C27) -> 0 | ... AH27: =SUMIFS(Data!$B$2:$B$100,Data!$A$2:$A$100,AH$2,Data!$D$2:$D$100,$C27) -> 0 | AI27: =SUM(D27:AH27) -> 91
C28: Total | D28: =SUM(D4:D27) -> 237 | E28: =SUM(E4:E27) -> 583.67 | F28: =SUM(F4:F27) -> 22 | G28: =SUM(G4:G27) -> 85 | H28: =SUM(H4:H27) -> 24 | I28: =SUM(I4:I27) -> 0 | J28: =SUM(J4:J27) -> 19 | K28: =SUM(K4:K27) -> 72 | ... AI28: =SUM(AI4:AI27) -> 2778.67
C30: Dia | D30: 1 | E30: =D30+1 -> 2 | F30: =E30+1 -> 3 | G30: =F30+1 -> 4 | H30: =G30+1 -> 5 | I30: =H30+1 -> 6 | J30: =I30+1 -> 7 | K30: =J30+1 -> 8 | L30: =K30+1 -> 9 | ... AH30: =AG30+1 -> 31 | AI30: Total Mes
A31: Presupuesto | B31: Clasificacion | C31: SubClasificacion
B32: Costo Fijo - Depto | C32: Luz | D32: =$AI32/Presupuesto!$H$6*D$30*0 -> 0 | E32: =$AI32/Presupuesto!$H$6*E$30*0 -> 0 | F32: =$AI32/Presupuesto!$H$6*F$30*0 -> 0 | G32: =$AI32/Presupuesto!$H$6*G$30*0 -> 0 | H32: =$AI32/Presupuesto!$H$6*H$30*0 -> 0 | I32: =$AI32/Presupuesto!$H$6*I$30*0 -> 0 | J32: =$AI32/Presupuesto!$H$6*J$30*0 -> 0 | K32: =$AI32/Presupuesto!$H$6*K$30*0 -> 0 | ... AH32: =$AI32/Presupuesto!$H$6*AH$30*0 -> 0 | AI32: =Presupuesto!K7*0 -> 0
B33: Costo Fijo - Depto | C33: Internet | D33: =$AI33/Presupuesto!$H$6*D$30 -> 2.8387097 | E33: =$AI33/Presupuesto!$H$6*E$30 -> 5.6774194 | F33: =$AI33/Presupuesto!$H$6*F$30 -> 8.516129 | G33: =$AI33/Presupuesto!$H$6*G$30 -> 11.354839 | H33: =$AI33/Presupuesto!$H$6*H$30 -> 14.193548 | I33: =$AI33/Presupuesto!$H$6*I$30 -> 17.032258 | J33: =$AI33/Presupuesto!$H$6*J$30 -> 19.870968 | K33: =$AI33/Presupuesto!$H$6*K$30 -> 22.709677 | ... AH33: =$AI33/Presupuesto!$H$6*AH$30 -> 88 | AI33: =Presupuesto!K8 -> 88
B34: Costo Variable - Comidas | C34: Desayuno | D34: =$AI34/Presupuesto!$H$6*D$30 -> 4.1612903 | E34: =$AI34/Presupuesto!$H$6*E$30 -> 8.3225806 | F34: =$AI34/Presupuesto!$H$6*F$30 -> 12.483871 | G34: =$AI34/Presupuesto!$H$6*G$30 -> 16.645161 | H34: =$AI34/Presupuesto!$H$6*H$30 -> 20.806452 | I34: =$AI34/Presupuesto!$H$6*I$30 -> 24.967742 | J34: =$AI34/Presupuesto!$H$6*J$30 -> 29.129032 | K34: =$AI34/Presupuesto!$H$6*K$30 -> 33.290323 | ... AH34: =$AI34/Presupuesto!$H$6*AH$30 -> 129 | AI34: =Presupuesto!K11 -> 129
B35: Costo Variable - Comidas | C35: Almuerzo | D35: =$AI35/Presupuesto!$H$6*D$30 -> 11.096774 | E35: =$AI35/Presupuesto!$H$6*E$30 -> 22.193548 | F35: =$AI35/Presupuesto!$H$6*F$30 -> 33.290323 | G35: =$AI35/Presupuesto!$H$6*G$30 -> 44.387097 | H35: =$AI35/Presupuesto!$H$6*H$30 -> 55.483871 | I35: =$AI35/Presupuesto!$H$6*I$30 -> 66.580645 | J35: =$AI35/Presupuesto!$H$6*J$30 -> 77.677419 | K35: =$AI35/Presupuesto!$H$6*K$30 -> 88.774194 | ... AH35: =$AI35/Presupuesto!$H$6*AH$30 -> 344 | AI35: =Presupuesto!K12 -> 344
B36: Costo Variable - Comidas | C36: Cena | D36: =$AI36/Presupuesto!$H$6*D$30 -> 6.9354839 | E36: =$AI36/Presupuesto!$H$6*E$30 -> 13.870968 | F36: =$AI36/Presupuesto!$H$6*F$30 -> 20.806452 | G36: =$AI36/Presupuesto!$H$6*G$30 -> 27.741935 | H36: =$AI36/Presupuesto!$H$6*H$30 -> 34.677419 | I36: =$AI36/Presupuesto!$H$6*I$30 -> 41.612903 | J36: =$AI36/Presupuesto!$H$6*J$30 -> 48.548387 | K36: =$AI36/Presupuesto!$H$6*K$30 -> 55.483871 | ... AH36: =$AI36/Presupuesto!$H$6*AH$30 -> 215 | AI36: =Presupuesto!K13 -> 215
B37: Costo Variable - Comidas | C37: Super | D37: =$AI37/Presupuesto!$H$6*D$30 -> 20.806452 | E37: =$AI37/Presupuesto!$H$6*E$30 -> 41.612903 | F37: =$AI37/Presupuesto!$H$6*F$30 -> 62.419355 | G37: =$AI37/Presupuesto!$H$6*G$30 -> 83.225806 | H37: =$AI37/Presupuesto!$H$6*H$30 -> 104.03226 | I37: =$AI37/Presupuesto!$H$6*I$30 -> 124.83871 | J37: =$AI37/Presupuesto!$H$6*J$30 -> 145.64516 | K37: =$AI37/Presupuesto!$H$6*K$30 -> 166.45161 | ... AH37: =$AI37/Presupuesto!$H$6*AH$30 -> 645 | AI37: =Presupuesto!K14 -> 645
B38: Costo Variable - Otros | C38: Otros Casa | D38: =$AI38/Presupuesto!$H$6*D$30 -> 6.9354839 | E38: =$AI38/Presupuesto!$H$6*E$30 -> 13.870968 | F38: =$AI38/Presupuesto!$H$6*F$30 -> 20.806452 | G38: =$AI38/Presupuesto!$H$6*G$30 -> 27.741935 | H38: =$AI38/Presupuesto!$H$6*H$30 -> 34.677419 | I38: =$AI38/Presupuesto!$H$6*I$30 -> 41.612903 | J38: =$AI38/Presupuesto!$H$6*J$30 -> 48.548387 | K38: =$AI38/Presupuesto!$H$6*K$30 -> 55.483871 | ... AH38: =$AI38/Presupuesto!$H$6*AH$30 -> 215 | AI38: =Presupuesto!K15 -> 215
B39: Costo Variable - Otros | C39: Corte Pelo - Salud - Remedios | D39: =$AI39/Presupuesto!$H$6*D$30 -> 3.2258065 | E39: =$AI39/Presupuesto!$H$6*E$30 -> 6.4516129 | F39: =$AI39/Presupuesto!$H$6*F$30 -> 9.6774194 | G39: =$AI39/Presupuesto!$H$6*G$30 -> 12.903226 | H39: =$AI39/Presupuesto!$H$6*H$30 -> 16.129032 | I39: =$AI39/Presupuesto!$H$6*I$30 -> 19.354839 | J39: =$AI39/Presupuesto!$H$6*J$30 -> 22.580645 | K39: =$AI39/Presupuesto!$H$6*K$30 -> 25.806452 | ... AH39: =$AI39/Presupuesto!$H$6*AH$30 -> 100 | AI39: =Presupuesto!K16 -> 100
B40: Costo Variable - Otros | C40: Otros | D40: =$AI40/Presupuesto!$H$6*D$30 -> 5.5483871 | E40: =$AI40/Presupuesto!$H$6*E$30 -> 11.096774 | F40: =$AI40/Presupuesto!$H$6*F$30 -> 16.645161 | G40: =$AI40/Presupuesto!$H$6*G$30 -> 22.193548 | H40: =$AI40/Presupuesto!$H$6*H$30 -> 27.741935 | I40: =$AI40/Presupuesto!$H$6*I$30 -> 33.290323 | J40: =$AI40/Presupuesto!$H$6*J$30 -> 38.83871 | K40: =$AI40/Presupuesto!$H$6*K$30 -> 44.387097 | ... AH40: =$AI40/Presupuesto!$H$6*AH$30 -> 172 | AI40: =Presupuesto!K17 -> 172
B41: Costo Variable - Transporte | C41: Transporte - Scooter | D41: =$AI41/Presupuesto!$H$6*D$30 -> 1.6129032 | E41: =$AI41/Presupuesto!$H$6*E$30 -> 3.2258065 | F41: =$AI41/Presupuesto!$H$6*F$30 -> 4.8387097 | G41: =$AI41/Presupuesto!$H$6*G$30 -> 6.4516129 | H41: =$AI41/Presupuesto!$H$6*H$30 -> 8.0645161 | I41: =$AI41/Presupuesto!$H$6*I$30 -> 9.6774194 | J41: =$AI41/Presupuesto!$H$6*J$30 -> 11.290323 | K41: =$AI41/Presupuesto!$H$6*K$30 -> 12.903226 | ... AH41: =$AI41/Presupuesto!$H$6*AH$30 -> 50 | AI41: =Presupuesto!K18 -> 50
B42: Costo Variable - Transporte | C42: Uber | D42: =$AI42/Presupuesto!$H$6*D$30 -> 3.8709677 | E42: =$AI42/Presupuesto!$H$6*E$30 -> 7.7419355 | F42: =$AI42/Presupuesto!$H$6*F$30 -> 11.612903 | G42: =$AI42/Presupuesto!$H$6*G$30 -> 15.483871 | H42: =$AI42/Presupuesto!$H$6*H$30 -> 19.354839 | I42: =$AI42/Presupuesto!$H$6*I$30 -> 23.225806 | J42: =$AI42/Presupuesto!$H$6*J$30 -> 27.096774 | K42: =$AI42/Presupuesto!$H$6*K$30 -> 30.967742 | ... AH42: =$AI42/Presupuesto!$H$6*AH$30 -> 120 | AI42: =Presupuesto!K19 -> 120
B43: Costo Variable - Auto | C43: Bencina | D43: =$AI43/Presupuesto!$H$6*D$30 -> 2.5806452 | E43: =$AI43/Presupuesto!$H$6*E$30 -> 5.1612903 | F43: =$AI43/Presupuesto!$H$6*F$30 -> 7.7419355 | G43: =$AI43/Presupuesto!$H$6*G$30 -> 10.322581 | H43: =$AI43/Presupuesto!$H$6*H$30 -> 12.903226 | I43: =$AI43/Presupuesto!$H$6*I$30 -> 15.483871 | J43: =$AI43/Presupuesto!$H$6*J$30 -> 18.064516 | K43: =$AI43/Presupuesto!$H$6*K$30 -> 20.645161 | ... AH43: =$AI43/Presupuesto!$H$6*AH$30 -> 80 | AI43: =Presupuesto!K20 -> 80
B44: Costo Variable - Auto | C44: Seguro | D44: =$AI44/Presupuesto!$H$6*D$30 -> 3.2258065 | E44: =$AI44/Presupuesto!$H$6*E$30 -> 6.4516129 | F44: =$AI44/Presupuesto!$H$6*F$30 -> 9.6774194 | G44: =$AI44/Presupuesto!$H$6*G$30 -> 12.903226 | H44: =$AI44/Presupuesto!$H$6*H$30 -> 16.129032 | I44: =$AI44/Presupuesto!$H$6*I$30 -> 19.354839 | J44: =$AI44/Presupuesto!$H$6*J$30 -> 22.580645 | K44: =$AI44/Presupuesto!$H$6*K$30 -> 25.806452 | ... AH44: =$AI44/Presupuesto!$H$6*AH$30 -> 100 | AI44: =Presupuesto!K21 -> 100
B45: Costo Variable - Auto | C45: Estacionamiento - CarWash | D45: =$AI45/Presupuesto!$H$6*D$30 -> 1.1290323 | E45: =$AI45/Presupuesto!$H$6*E$30 -> 2.2580645 | F45: =$AI45/Presupuesto!$H$6*F$30 -> 3.3870968 | G45: =$AI45/Presupuesto!$H$6*G$30 -> 4.516129 | H45: =$AI45/Presupuesto!$H$6*H$30 -> 5.6451613 | I45: =$AI45/Presupuesto!$H$6*I$30 -> 6.7741935 | J45: =$AI45/Presupuesto!$H$6*J$30 -> 7.9032258 | K45: =$AI45/Presupuesto!$H$6*K$30 -> 9.0322581 | ... AH45: =$AI45/Presupuesto!$H$6*AH$30 -> 35 | AI45: =Presupuesto!K22 -> 35
B46: Costo Variable - Auto | C46: Mecanico | D46: =$AI46/Presupuesto!$H$6*D$30*0 -> 0 | E46: =$AI46/Presupuesto!$H$6*E$30*0 -> 0 | F46: =$AI46/Presupuesto!$H$6*F$30*0 -> 0 | G46: =$AI46/Presupuesto!$H$6*G$30*0 -> 0 | H46: =$AI46/Presupuesto!$H$6*H$30*0 -> 0 | I46: =$AI46/Presupuesto!$H$6*I$30*0 -> 0 | J46: =$AI46/Presupuesto!$H$6*J$30*0 -> 0 | K46: =$AI46/Presupuesto!$H$6*K$30*0 -> 0 | ... AH46: =$AI46/Presupuesto!$H$6*AH$30*0 -> 0 | AI46: =Presupuesto!K23*0 -> 0
B47: Costo Variable - Auto | C47: REGO | D47: =$AI47/Presupuesto!$H$6*D$30*0 -> 0 | E47: =$AI47/Presupuesto!$H$6*E$30*0 -> 0 | F47: =$AI47/Presupuesto!$H$6*F$30*0 -> 0 | G47: =$AI47/Presupuesto!$H$6*G$30*0 -> 0 | H47: =$AI47/Presupuesto!$H$6*H$30*0 -> 0 | I47: =$AI47/Presupuesto!$H$6*I$30*0 -> 0 | J47: =$AI47/Presupuesto!$H$6*J$30*0 -> 0 | K47: =$AI47/Presupuesto!$H$6*K$30*0 -> 0 | ... AH47: =$AI47/Presupuesto!$H$6*AH$30*0 -> 0 | AI47: =Presupuesto!K24*0 -> 0
B48: Costo Variable - Auto | C48: Peajes | D48: =$AI48/Presupuesto!$H$6*D$30 -> 1.2903226 | E48: =$AI48/Presupuesto!$H$6*E$30 -> 2.5806452 | F48: =$AI48/Presupuesto!$H$6*F$30 -> 3.8709677 | G48: =$AI48/Presupuesto!$H$6*G$30 -> 5.1612903 | H48: =$AI48/Presupuesto!$H$6*H$30 -> 6.4516129 | I48: =$AI48/Presupuesto!$H$6*I$30 -> 7.7419355 | J48: =$AI48/Presupuesto!$H$6*J$30 -> 9.0322581 | K48: =$AI48/Presupuesto!$H$6*K$30 -> 10.322581 | ... AH48: =$AI48/Presupuesto!$H$6*AH$30 -> 40 | AI48: =Presupuesto!K25 -> 40
B49: Costo Variable - Gasto Pega | C49: Uber Pega | D49: =$AI49/Presupuesto!$H$6*D$30 -> 7.6290323 | E49: =$AI49/Presupuesto!$H$6*E$30 -> 15.258065 | F49: =$AI49/Presupuesto!$H$6*F$30 -> 22.887097 | G49: =$AI49/Presupuesto!$H$6*G$30 -> 30.516129 | H49: =$AI49/Presupuesto!$H$6*H$30 -> 38.145161 | I49: =$AI49/Presupuesto!$H$6*I$30 -> 45.774194 | J49: =$AI49/Presupuesto!$H$6*J$30 -> 53.403226 | K49: =$AI49/Presupuesto!$H$6*K$30 -> 61.032258 | ... AH49: =$AI49/Presupuesto!$H$6*AH$30 -> 236.5 | AI49: =Presupuesto!K26 -> 236.5
B50: Costo Variable - Gasto Pega | C50: Tren - GoCard - Scooter Pega | D50: =$AI50/Presupuesto!$H$6*D$30 -> 3.1903226 | E50: =$AI50/Presupuesto!$H$6*E$30 -> 6.3806452 | F50: =$AI50/Presupuesto!$H$6*F$30 -> 9.5709677 | G50: =$AI50/Presupuesto!$H$6*G$30 -> 12.76129 | H50: =$AI50/Presupuesto!$H$6*H$30 -> 15.951613 | I50: =$AI50/Presupuesto!$H$6*I$30 -> 19.141935 | J50: =$AI50/Presupuesto!$H$6*J$30 -> 22.332258 | K50: =$AI50/Presupuesto!$H$6*K$30 -> 25.522581 | ... AH50: =$AI50/Presupuesto!$H$6*AH$30 -> 98.9 | AI50: =Presupuesto!K27 -> 98.9
B51: Costo Variable - Gasto Pega | C51: Parking - Otros Pega | D51: =$AI51/Presupuesto!$H$6*D$30 -> 3.883871 | E51: =$AI51/Presupuesto!$H$6*E$30 -> 7.7677419 | F51: =$AI51/Presupuesto!$H$6*F$30 -> 11.651613 | G51: =$AI51/Presupuesto!$H$6*G$30 -> 15.535484 | H51: =$AI51/Presupuesto!$H$6*H$30 -> 19.419355 | I51: =$AI51/Presupuesto!$H$6*I$30 -> 23.303226 | J51: =$AI51/Presupuesto!$H$6*J$30 -> 27.187097 | K51: =$AI51/Presupuesto!$H$6*K$30 -> 31.070968 | ... AH51: =$AI51/Presupuesto!$H$6*AH$30 -> 120.4 | AI51: =Presupuesto!K28 -> 120.4
B52: Costo Variable - Personales | C52: Otros Personales | D52: =$AI52/Presupuesto!$H$6*D$30 -> 4.8387097 | E52: =$AI52/Presupuesto!$H$6*E$30 -> 9.6774194 | F52: =$AI52/Presupuesto!$H$6*F$30 -> 14.516129 | G52: =$AI52/Presupuesto!$H$6*G$30 -> 19.354839 | H52: =$AI52/Presupuesto!$H$6*H$30 -> 24.193548 | I52: =$AI52/Presupuesto!$H$6*I$30 -> 29.032258 | J52: =$AI52/Presupuesto!$H$6*J$30 -> 33.870968 | K52: =$AI52/Presupuesto!$H$6*K$30 -> 38.709677 | ... AH52: =$AI52/Presupuesto!$H$6*AH$30 -> 150 | AI52: =Presupuesto!K29 -> 150
B53: Costo Variable - Personales | C53: Libros - Cursos | D53: =$AI53/Presupuesto!$H$6*D$30 -> 4.1612903 | E53: =$AI53/Presupuesto!$H$6*E$30 -> 8.3225806 | F53: =$AI53/Presupuesto!$H$6*F$30 -> 12.483871 | G53: =$AI53/Presupuesto!$H$6*G$30 -> 16.645161 | H53: =$AI53/Presupuesto!$H$6*H$30 -> 20.806452 | I53: =$AI53/Presupuesto!$H$6*I$30 -> 24.967742 | J53: =$AI53/Presupuesto!$H$6*J$30 -> 29.129032 | K53: =$AI53/Presupuesto!$H$6*K$30 -> 33.290323 | ... AH53: =$AI53/Presupuesto!$H$6*AH$30 -> 129 | AI53: =Presupuesto!K30 -> 129
B54: Costo Variable - Personales | C54: Ropa - Accesorios | D54: =$AI54/Presupuesto!$H$6*D$30 -> 2.7741935 | E54: =$AI54/Presupuesto!$H$6*E$30 -> 5.5483871 | F54: =$AI54/Presupuesto!$H$6*F$30 -> 8.3225806 | G54: =$AI54/Presupuesto!$H$6*G$30 -> 11.096774 | H54: =$AI54/Presupuesto!$H$6*H$30 -> 13.870968 | I54: =$AI54/Presupuesto!$H$6*I$30 -> 16.645161 | J54: =$AI54/Presupuesto!$H$6*J$30 -> 19.419355 | K54: =$AI54/Presupuesto!$H$6*K$30 -> 22.193548 | ... AH54: =$AI54/Presupuesto!$H$6*AH$30 -> 86 | AI54: =Presupuesto!K31 -> 86
B55: Costo Variable - Personales | C55: Regalos - Eventos | D55: =$AI55/Presupuesto!$H$6*D$30 -> 0 | E55: =$AI55/Presupuesto!$H$6*E$30 -> 0 | F55: =$AI55/Presupuesto!$H$6*F$30 -> 0 | G55: =$AI55/Presupuesto!$H$6*G$30 -> 0 | H55: =$AI55/Presupuesto!$H$6*H$30 -> 0 | I55: =$AI55/Presupuesto!$H$6*I$30 -> 0 | J55: =$AI55/Presupuesto!$H$6*J$30 -> 0 | K55: =$AI55/Presupuesto!$H$6*K$30 -> 0 | ... AH55: =$AI55/Presupuesto!$H$6*AH$30 -> 0 | AI55: =Presupuesto!K32
C56: Total | D56: =SUM(D32:D54) -> 101.73548 | E56: =SUM(E32:E54) -> 203.47097 | F56: =SUM(F32:F54) -> 305.20645 | G56: =SUM(G32:G54) -> 406.94194 | H56: =SUM(H32:H54) -> 508.67742 | I56: =SUM(I32:I54) -> 610.4129 | J56: =SUM(J32:J54) -> 712.14839 | K56: =SUM(K32:K54) -> 813.88387 | ... AI56: =SUM(AI32:AI54) -> 3153.8
B58: Acumulado | C58: Dia | D58: 1 | E58: =D58+1 -> 2 | F58: =E58+1 -> 3 | G58: =F58+1 -> 4 | H58: =G58+1 -> 5 | I58: =H58+1 -> 6 | J58: =I58+1 -> 7 | K58: =J58+1 -> 8 | L58: =K58+1 -> 9 | ... AH58: =AG58+1 -> 31 | AI58: Total Mes | AJ58: Max Dia
B59: Clasificacion | C59: SubClasificacion | AJ59: =MAX(Data!A:A) -> 31
B60: Costo Fijo - Depto | C60: Luz | D60: =if($AJ$59>=D$58,D4,0)*0 -> 0 | E60: =if($AJ$59>=E$58,E4,0)*0 -> 0 | F60: =if($AJ$59>=F$58,F4,0)*0 -> 0 | G60: =if($AJ$59>=G$58,G4,0)*0 -> 0 | H60: =if($AJ$59>=H$58,H4,0)*0 -> 0 | I60: =if($AJ$59>=I$58,I4,0)*0 -> 0 | J60: =if($AJ$59>=J$58,J4,0)*0 -> 0 | K60: =if($AJ$59>=K$58,K4,0)*0 -> 0 | ... AH60: =if($AJ$59>=AH$58,AH4,0)*0 -> 0 | AI60: =INDEX(D60:AH60, $AJ$59) -> 0
B61: Costo Fijo - Depto | C61: Internet | D61: =if($AJ$59>=D$58,D5,0) -> 95 | E61: =if($AJ$59>=E$58,D61+E5,0) -> 95 | F61: =if($AJ$59>=F$58,E61+F5,0) -> 95 | G61: =if($AJ$59>=G$58,F61+G5,0) -> 95 | H61: =if($AJ$59>=H$58,G61+H5,0) -> 95 | I61: =if($AJ$59>=I$58,H61+I5,0) -> 95 | J61: =if($AJ$59>=J$58,I61+J5,0) -> 95 | K61: =if($AJ$59>=K$58,J61+K5,0) -> 95 | L61: =if($AJ$59>=L$58,K61+L5,0) -> 95 | ... AH61: =if($AJ$59>=AH$58,AG61+AH5,0) -> 95 | AI61: =INDEX(D61:AH61, $AJ$59) -> 95
B62: Costo Variable - Comidas | C62: Desayuno | D62: =if($AJ$59>=D$58,D6,0) -> 11 | E62: =if($AJ$59>=E$58,D62+E6,0) -> 11 | F62: =if($AJ$59>=F$58,E62+F6,0) -> 33 | G62: =if($AJ$59>=G$58,F62+G6,0) -> 33 | H62: =if($AJ$59>=H$58,G62+H6,0) -> 33 | I62: =if($AJ$59>=I$58,H62+I6,0) -> 33 | J62: =if($AJ$59>=J$58,I62+J6,0) -> 33 | K62: =if($AJ$59>=K$58,J62+K6,0) -> 33 | L62: =if($AJ$59>=L$58,K62+L6,0) -> 77 | ... AH62: =if($AJ$59>=AH$58,AG62+AH6,0) -> 156 | AI62: =INDEX(D62:AH62, $AJ$59) -> 156
B63: Costo Variable - Comidas | C63: Almuerzo | D63: =if($AJ$59>=D$58,D7,0) -> 0 | E63: =if($AJ$59>=E$58,D63+E7,0) -> 39 | F63: =if($AJ$59>=F$58,E63+F7,0) -> 39 | G63: =if($AJ$59>=G$58,F63+G7,0) -> 124 | H63: =if($AJ$59>=H$58,G63+H7,0) -> 124 | I63: =if($AJ$59>=I$58,H63+I7,0) -> 124 | J63: =if($AJ$59>=J$58,I63+J7,0) -> 124 | K63: =if($AJ$59>=K$58,J63+K7,0) -> 124 | L63: =if($AJ$59>=L$58,K63+L7,0) -> 124 | ... AH63: =if($AJ$59>=AH$58,AG63+AH7,0) -> 281 | AI63: =INDEX(D63:AH63, $AJ$59) -> 281
B64: Costo Variable - Comidas | C64: Cena | D64: =if($AJ$59>=D$58,D8,0) -> 0 | E64: =if($AJ$59>=E$58,D64+E8,0) -> 0 | F64: =if($AJ$59>=F$58,E64+F8,0) -> 0 | G64: =if($AJ$59>=G$58,F64+G8,0) -> 0 | H64: =if($AJ$59>=H$58,G64+H8,0) -> 24 | I64: =if($AJ$59>=I$58,H64+I8,0) -> 24 | J64: =if($AJ$59>=J$58,I64+J8,0) -> 40 | K64: =if($AJ$59>=K$58,J64+K8,0) -> 40 | L64: =if($AJ$59>=L$58,K64+L8,0) -> 40 | ... AH64: =if($AJ$59>=AH$58,AG64+AH8,0) -> 190 | AI64: =INDEX(D64:AH64, $AJ$59) -> 190
B65: Costo Variable - Comidas | C65: Super | D65: =if($AJ$59>=D$58,D9,0) -> 0 | E65: =if($AJ$59>=E$58,D65+E9,0) -> 110 | F65: =if($AJ$59>=F$58,E65+F9,0) -> 110 | G65: =if($AJ$59>=G$58,F65+G9,0) -> 110 | H65: =if($AJ$59>=H$58,G65+H9,0) -> 110 | I65: =if($AJ$59>=I$58,H65+I9,0) -> 110 | J65: =if($AJ$59>=J$58,I65+J9,0) -> 110 | K65: =if($AJ$59>=K$58,J65+K9,0) -> 120 | L65: =if($AJ$59>=L$58,K65+L9,0) -> 293 | ... AH65: =if($AJ$59>=AH$58,AG65+AH9,0) -> 866 | AI65: =INDEX(D65:AH65, $AJ$59) -> 866
B66: Costo Variable - Otros | C66: Otros Casa | D66: =if($AJ$59>=D$58,D10,0) -> 0 | E66: =if($AJ$59>=E$58,D66+E10,0) -> 0 | F66: =if($AJ$59>=F$58,E66+F10,0) -> 0 | G66: =if($AJ$59>=G$58,F66+G10,0) -> 0 | H66: =if($AJ$59>=H$58,G66+H10,0) -> 0 | I66: =if($AJ$59>=I$58,H66+I10,0) -> 0 | J66: =if($AJ$59>=J$58,I66+J10,0) -> 0 | K66: =if($AJ$59>=K$58,J66+K10,0) -> 0 | L66: =if($AJ$59>=L$58,K66+L10,0) -> 0 | ... AH66: =if($AJ$59>=AH$58,AG66+AH10,0) -> 0 | AI66: =INDEX(D66:AH66, $AJ$59) -> 0
B67: Costo Variable - Otros | C67: Corte Pelo - Salud - Remedios | D67: =if($AJ$59>=D$58,D11,0) -> 0 | E67: =if($AJ$59>=E$58,D67+E11,0) -> 0 | F67: =if($AJ$59>=F$58,E67+F11,0) -> 0 | G67: =if($AJ$59>=G$58,F67+G11,0) -> 0 | H67: =if($AJ$59>=H$58,G67+H11,0) -> 0 | I67: =if($AJ$59>=I$58,H67+I11,0) -> 0 | J67: =if($AJ$59>=J$58,I67+J11,0) -> 0 | K67: =if($AJ$59>=K$58,J67+K11,0) -> 56 | L67: =if($AJ$59>=L$58,K67+L11,0) -> 56 | ... AH67: =if($AJ$59>=AH$58,AG67+AH11,0) -> 112 | AI67: =INDEX(D67:AH67, $AJ$59) -> 112
B68: Costo Variable - Otros | C68: Otros | D68: =if($AJ$59>=D$58,D12,0) -> 0 | E68: =if($AJ$59>=E$58,D68+E12,0) -> 0 | F68: =if($AJ$59>=F$58,E68+F12,0) -> 0 | G68: =if($AJ$59>=G$58,F68+G12,0) -> 0 | H68: =if($AJ$59>=H$58,G68+H12,0) -> 0 | I68: =if($AJ$59>=I$58,H68+I12,0) -> 0 | J68: =if($AJ$59>=J$58,I68+J12,0) -> 0 | K68: =if($AJ$59>=K$58,J68+K12,0) -> 0 | L68: =if($AJ$59>=L$58,K68+L12,0) -> 0 | ... AH68: =if($AJ$59>=AH$58,AG68+AH12,0) -> 0 | AI68: =INDEX(D68:AH68, $AJ$59) -> 0
B69: Costo Variable - Transporte | C69: Transporte - Scooter | D69: =if($AJ$59>=D$58,D13,0) -> 0 | E69: =if($AJ$59>=E$58,D69+E13,0) -> 0 | F69: =if($AJ$59>=F$58,E69+F13,0) -> 0 | G69: =if($AJ$59>=G$58,F69+G13,0) -> 0 | H69: =if($AJ$59>=H$58,G69+H13,0) -> 0 | I69: =if($AJ$59>=I$58,H69+I13,0) -> 0 | J69: =if($AJ$59>=J$58,I69+J13,0) -> 3 | K69: =if($AJ$59>=K$58,J69+K13,0) -> 9 | L69: =if($AJ$59>=L$58,K69+L13,0) -> 12 | ... AH69: =if($AJ$59>=AH$58,AG69+AH13,0) -> 20 | AI69: =INDEX(D69:AH69, $AJ$59) -> 20
B70: Costo Variable - Transporte | C70: Uber | D70: =if($AJ$59>=D$58,D14,0) -> 0 | E70: =if($AJ$59>=E$58,D70+E14,0) -> 0 | F70: =if($AJ$59>=F$58,E70+F14,0) -> 0 | G70: =if($AJ$59>=G$58,F70+G14,0) -> 0 | H70: =if($AJ$59>=H$58,G70+H14,0) -> 0 | I70: =if($AJ$59>=I$58,H70+I14,0) -> 0 | J70: =if($AJ$59>=J$58,I70+J14,0) -> 0 | K70: =if($AJ$59>=K$58,J70+K14,0) -> 0 | L70: =if($AJ$59>=L$58,K70+L14,0) -> 0 | ... AH70: =if($AJ$59>=AH$58,AG70+AH14,0) -> 0 | AI70: =INDEX(D70:AH70, $AJ$59) -> 0
B71: Costo Variable - Auto | C71: Bencina | D71: =if($AJ$59>=D$58,D15,0) -> 0 | E71: =if($AJ$59>=E$58,D71+E15,0) -> 0 | F71: =if($AJ$59>=F$58,E71+F15,0) -> 0 | G71: =if($AJ$59>=G$58,F71+G15,0) -> 0 | H71: =if($AJ$59>=H$58,G71+H15,0) -> 0 | I71: =if($AJ$59>=I$58,H71+I15,0) -> 0 | J71: =if($AJ$59>=J$58,I71+J15,0) -> 0 | K71: =if($AJ$59>=K$58,J71+K15,0) -> 0 | L71: =if($AJ$59>=L$58,K71+L15,0) -> 0 | ... AH71: =if($AJ$59>=AH$58,AG71+AH15,0) -> 46 | AI71: =INDEX(D71:AH71, $AJ$59) -> 46
B72: Costo Variable - Auto | C72: Seguro | D72: =if($AJ$59>=D$58,D16,0) -> 0 | E72: =if($AJ$59>=E$58,D72+E16,0) -> 0 | F72: =if($AJ$59>=F$58,E72+F16,0) -> 0 | G72: =if($AJ$59>=G$58,F72+G16,0) -> 0 | H72: =if($AJ$59>=H$58,G72+H16,0) -> 0 | I72: =if($AJ$59>=I$58,H72+I16,0) -> 0 | J72: =if($AJ$59>=J$58,I72+J16,0) -> 0 | K72: =if($AJ$59>=K$58,J72+K16,0) -> 0 | L72: =if($AJ$59>=L$58,K72+L16,0) -> 0 | ... AH72: =if($AJ$59>=AH$58,AG72+AH16,0) -> 0 | AI72: =INDEX(D72:AH72, $AJ$59) -> 0
B73: Costo Variable - Auto | C73: Estacionamiento - CarWash | D73: =if($AJ$59>=D$58,D17,0) -> 0 | E73: =if($AJ$59>=E$58,D73+E17,0) -> 6 | F73: =if($AJ$59>=F$58,E73+F17,0) -> 6 | G73: =if($AJ$59>=G$58,F73+G17,0) -> 6 | H73: =if($AJ$59>=H$58,G73+H17,0) -> 6 | I73: =if($AJ$59>=I$58,H73+I17,0) -> 6 | J73: =if($AJ$59>=J$58,I73+J17,0) -> 6 | K73: =if($AJ$59>=K$58,J73+K17,0) -> 6 | L73: =if($AJ$59>=L$58,K73+L17,0) -> 6 | ... AH73: =if($AJ$59>=AH$58,AG73+AH17,0) -> 22 | AI73: =INDEX(D73:AH73, $AJ$59) -> 22
B74: Costo Variable - Auto | C74: Mecanico | D74: =if($AJ$59>=D$58,D18,0)*0 -> 0 | E74: =if($AJ$59>=E$58,E18,0)*0 -> 0 | F74: =if($AJ$59>=F$58,F18,0)*0 -> 0 | G74: =if($AJ$59>=G$58,G18,0)*0 -> 0 | H74: =if($AJ$59>=H$58,H18,0)*0 -> 0 | I74: =if($AJ$59>=I$58,I18,0)*0 -> 0 | J74: =if($AJ$59>=J$58,J18,0)*0 -> 0 | K74: =if($AJ$59>=K$58,K18,0)*0 -> 0 | ... AH74: =if($AJ$59>=AH$58,AH18,0)*0 -> 0 | AI74: =INDEX(D74:AH74, $AJ$59) -> 0
B75: Costo Variable - Auto | C75: REGO | D75: =if($AJ$59>=D$58,D19,0)*0 -> 0 | E75: =if($AJ$59>=E$58,E19,0)*0 -> 0 | F75: =if($AJ$59>=F$58,F19,0)*0 -> 0 | G75: =if($AJ$59>=G$58,G19,0)*0 -> 0 | H75: =if($AJ$59>=H$58,H19,0)*0 -> 0 | I75: =if($AJ$59>=I$58,I19,0)*0 -> 0 | J75: =if($AJ$59>=J$58,J19,0)*0 -> 0 | K75: =if($AJ$59>=K$58,K19,0)*0 -> 0 | ... AH75: =if($AJ$59>=AH$58,AH19,0)*0 -> 0 | AI75: =INDEX(D75:AH75, $AJ$59) -> 0
B76: Costo Variable - Auto | C76: Peajes | D76: =if($AJ$59>=D$58,D20,0) -> 0 | E76: =if($AJ$59>=E$58,D76+E20,0) -> 0 | F76: =if($AJ$59>=F$58,E76+F20,0) -> 0 | G76: =if($AJ$59>=G$58,F76+G20,0) -> 0 | H76: =if($AJ$59>=H$58,G76+H20,0) -> 0 | I76: =if($AJ$59>=I$58,H76+I20,0) -> 0 | J76: =if($AJ$59>=J$58,I76+J20,0) -> 0 | K76: =if($AJ$59>=K$58,J76+K20,0) -> 0 | L76: =if($AJ$59>=L$58,K76+L20,0) -> 0 | ... AH76: =if($AJ$59>=AH$58,AG76+AH20,0) -> 42 | AI76: =INDEX(D76:AH76, $AJ$59) -> 42
B77: Costo Variable - Gasto Pega | C77: Uber Pega | D77: =if($AJ$59>=D$58,D21,0) -> 0 | E77: =if($AJ$59>=E$58,D77+E21,0) -> 0 | F77: =if($AJ$59>=F$58,E77+F21,0) -> 0 | G77: =if($AJ$59>=G$58,F77+G21,0) -> 0 | H77: =if($AJ$59>=H$58,G77+H21,0) -> 0 | I77: =if($AJ$59>=I$58,H77+I21,0) -> 0 | J77: =if($AJ$59>=J$58,I77+J21,0) -> 0 | K77: =if($AJ$59>=K$58,J77+K21,0) -> 0 | L77: =if($AJ$59>=L$58,K77+L21,0) -> 0 | ... AH77: =if($AJ$59>=AH$58,AG77+AH21,0) -> 202 | AI77: =INDEX(D77:AH77, $AJ$59) -> 202
B78: Costo Variable - Gasto Pega | C78: Tren - GoCard - Scooter Pega | D78: =if($AJ$59>=D$58,D22,0) -> 0 | E78: =if($AJ$59>=E$58,D78+E22,0) -> 0 | F78: =if($AJ$59>=F$58,E78+F22,0) -> 0 | G78: =if($AJ$59>=G$58,F78+G22,0) -> 0 | H78: =if($AJ$59>=H$58,G78+H22,0) -> 0 | I78: =if($AJ$59>=I$58,H78+I22,0) -> 0 | J78: =if($AJ$59>=J$58,I78+J22,0) -> 0 | K78: =if($AJ$59>=K$58,J78+K22,0) -> 0 | L78: =if($AJ$59>=L$58,K78+L22,0) -> 0 | ... AH78: =if($AJ$59>=AH$58,AG78+AH22,0) -> 89 | AI78: =INDEX(D78:AH78, $AJ$59) -> 89
B79: Costo Variable - Gasto Pega | C79: Parking - Otros Pega | D79: =if($AJ$59>=D$58,D23,0) -> 0 | E79: =if($AJ$59>=E$58,D79+E23,0) -> 0 | F79: =if($AJ$59>=F$58,E79+F23,0) -> 0 | G79: =if($AJ$59>=G$58,F79+G23,0) -> 0 | H79: =if($AJ$59>=H$58,G79+H23,0) -> 0 | I79: =if($AJ$59>=I$58,H79+I23,0) -> 0 | J79: =if($AJ$59>=J$58,I79+J23,0) -> 0 | K79: =if($AJ$59>=K$58,J79+K23,0) -> 0 | L79: =if($AJ$59>=L$58,K79+L23,0) -> 0 | ... AH79: =if($AJ$59>=AH$58,AG79+AH23,0) -> 0 | AI79: =INDEX(D79:AH79, $AJ$59) -> 0
B80: Costo Variable - Personales | C80: Otros Personales | D80: =if($AJ$59>=D$58,D24,0) -> 131 | E80: =if($AJ$59>=E$58,D80+E24,0) -> 331.67 | F80: =if($AJ$59>=F$58,E80+F24,0) -> 331.67 | G80: =if($AJ$59>=G$58,F80+G24,0) -> 331.67 | H80: =if($AJ$59>=H$58,G80+H24,0) -> 331.67 | I80: =if($AJ$59>=I$58,H80+I24,0) -> 331.67 | J80: =if($AJ$59>=J$58,I80+J24,0) -> 331.67 | K80: =if($AJ$59>=K$58,J80+K24,0) -> 331.67 | L80: =if($AJ$59>=L$58,K80+L24,0) -> 331.67 | ... AH80: =if($AJ$59>=AH$58,AG80+AH24,0) -> 388.67 | AI80: =INDEX(D80:AH80, $AJ$59) -> 388.67
B81: Costo Variable - Personales | C81: Libros - Cursos | D81: =if($AJ$59>=D$58,D25,0) -> 0 | E81: =if($AJ$59>=E$58,D81+E25,0) -> 0 | F81: =if($AJ$59>=F$58,E81+F25,0) -> 0 | G81: =if($AJ$59>=G$58,F81+G25,0) -> 0 | H81: =if($AJ$59>=H$58,G81+H25,0) -> 0 | I81: =if($AJ$59>=I$58,H81+I25,0) -> 0 | J81: =if($AJ$59>=J$58,I81+J25,0) -> 0 | K81: =if($AJ$59>=K$58,J81+K25,0) -> 0 | L81: =if($AJ$59>=L$58,K81+L25,0) -> 0 | ... AH81: =if($AJ$59>=AH$58,AG81+AH25,0) -> 0 | AI81: =INDEX(D81:AH81, $AJ$59) -> 0
B82: Costo Variable - Personales | C82: Ropa - Accesorios | D82: =if($AJ$59>=D$58,D26,0) -> 0 | E82: =if($AJ$59>=E$58,D82+E26,0) -> 178 | F82: =if($AJ$59>=F$58,E82+F26,0) -> 178 | G82: =if($AJ$59>=G$58,F82+G26,0) -> 178 | H82: =if($AJ$59>=H$58,G82+H26,0) -> 178 | I82: =if($AJ$59>=I$58,H82+I26,0) -> 178 | J82: =if($AJ$59>=J$58,I82+J26,0) -> 178 | K82: =if($AJ$59>=K$58,J82+K26,0) -> 178 | L82: =if($AJ$59>=L$58,K82+L26,0) -> 178 | ... AH82: =if($AJ$59>=AH$58,AG82+AH26,0) -> 178 | AI82: =INDEX(D82:AH82, $AJ$59) -> 178
B83: Costo Variable - Personales | C83: Regalos - Eventos | D83: =if($AJ$59>=D$58,D27,0) -> 0 | E83: =if($AJ$59>=E$58,D83+E27,0) -> 50 | F83: =if($AJ$59>=F$58,E83+F27,0) -> 50 | G83: =if($AJ$59>=G$58,F83+G27,0) -> 50 | H83: =if($AJ$59>=H$58,G83+H27,0) -> 50 | I83: =if($AJ$59>=I$58,H83+I27,0) -> 50 | J83: =if($AJ$59>=J$58,I83+J27,0) -> 50 | K83: =if($AJ$59>=K$58,J83+K27,0) -> 50 | L83: =if($AJ$59>=L$58,K83+L27,0) -> 50 | ... AH83: =if($AJ$59>=AH$58,AG83+AH27,0) -> 91 | AI83: =INDEX(D83:AH83, $AJ$59) -> 91
C84: Total | D84: =sum(D60:D83) -> 237 | E84: =sum(E60:E83) -> 820.67 | F84: =sum(F60:F83) -> 842.67 | G84: =sum(G60:G83) -> 927.67 | H84: =sum(H60:H83) -> 951.67 | I84: =sum(I60:I83) -> 951.67 | J84: =sum(J60:J83) -> 970.67 | K84: =sum(K60:K83) -> 1042.67 | ... AI84: =sum(AI60:AI83) -> 2778.67
C86: Dia | D86: =D58 -> 1 | E86: =E58 -> 2 | F86: =F58 -> 3 | G86: =G58 -> 4 | H86: =H58 -> 5 | I86: =I58 -> 6 | J86: =J58 -> 7 | K86: =K58 -> 8 | ... AH86: =AH58 -> 31
C87: Luz - Plan | D87: =D32 -> 0 | E87: =E32 -> 0 | F87: =F32 -> 0 | G87: =G32 -> 0 | H87: =H32 -> 0 | I87: =I32 -> 0 | J87: =J32 -> 0 | K87: =K32 -> 0 | ... AH87: =AH32 -> 0
C88: Internet - Plan | D88: =D33 -> 2.8387097 | E88: =E33 -> 5.6774194 | F88: =F33 -> 8.516129 | G88: =G33 -> 11.354839 | H88: =H33 -> 14.193548 | I88: =I33 -> 17.032258 | J88: =J33 -> 19.870968 | K88: =K33 -> 22.709677 | ... AH88: =AH33 -> 88
C89: Luz - Real | D89: =D60 -> 0 | E89: =E60 -> 0 | F89: =F60 -> 0 | G89: =G60 -> 0 | H89: =H60 -> 0 | I89: =I60 -> 0 | J89: =J60 -> 0 | K89: =K60 -> 0 | ... AH89: =AH60 -> 0
C90: Internet - Real | D90: =D61 -> 95 | E90: =E61 -> 95 | F90: =F61 -> 95 | G90: =G61 -> 95 | H90: =H61 -> 95 | I90: =I61 -> 95 | J90: =J61 -> 95 | K90: =K61 -> 95 | ... AH90: =AH61 -> 95
C110: Dia | D110: =D86 -> 1 | E110: =E86 -> 2 | F110: =F86 -> 3 | G110: =G86 -> 4 | H110: =H86 -> 5 | I110: =I86 -> 6 | J110: =J86 -> 7 | K110: =K86 -> 8 | ... AH110: =AH86 -> 31
C111: Comidas - Plan | D111: =D34+D35+D36 -> 22.193548 | E111: =E34+E35+E36 -> 44.387097 | F111: =F34+F35+F36 -> 66.580645 | G111: =G34+G35+G36 -> 88.774194 | H111: =H34+H35+H36 -> 110.96774 | I111: =I34+I35+I36 -> 133.16129 | J111: =J34+J35+J36 -> 155.35484 | K111: =K34+K35+K36 -> 177.54839 | ... AH111: =AH34+AH35+AH36 -> 688
C112: Comidas Real | D112: =D62+D63+D64 -> 11 | E112: =E62+E63+E64 -> 50 | F112: =F62+F63+F64 -> 72 | G112: =G62+G63+G64 -> 157 | H112: =H62+H63+H64 -> 181 | I112: =I62+I63+I64 -> 181 | J112: =J62+J63+J64 -> 197 | K112: =K62+K63+K64 -> 197 | ... AH112: =AH62+AH63+AH64 -> 627
C113: Super - Plan | D113: =D37 -> 20.806452 | E113: =E37 -> 41.612903 | F113: =F37 -> 62.419355 | G113: =G37 -> 83.225806 | H113: =H37 -> 104.03226 | I113: =I37 -> 124.83871 | J113: =J37 -> 145.64516 | K113: =K37 -> 166.45161 | ... AH113: =AH37 -> 645
C114: Super - Real | D114: =D65 -> 0 | E114: =E65 -> 110 | F114: =F65 -> 110 | G114: =G65 -> 110 | H114: =H65 -> 110 | I114: =I65 -> 110 | J114: =J65 -> 110 | K114: =K65 -> 120 | ... AH114: =AH65 -> 866
C115: Otros - Plan | D115: =D38+D39+D40 -> 15.709677 | E115: =E38+E39+E40 -> 31.419355 | F115: =F38+F39+F40 -> 47.129032 | G115: =G38+G39+G40 -> 62.83871 | H115: =H38+H39+H40 -> 78.548387 | I115: =I38+I39+I40 -> 94.258065 | J115: =J38+J39+J40 -> 109.96774 | K115: =K38+K39+K40 -> 125.67742 | ... AH115: =AH38+AH39+AH40 -> 487
C116: Otros - Real | D116: =D66+D67+D68 -> 0 | E116: =E66+E67+E68 -> 0 | F116: =F66+F67+F68 -> 0 | G116: =G66+G67+G68 -> 0 | H116: =H66+H67+H68 -> 0 | I116: =I66+I67+I68 -> 0 | J116: =J66+J67+J68 -> 0 | K116: =K66+K67+K68 -> 56 | ... AH116: =AH66+AH67+AH68 -> 112
C137: Dia | D137: =D110 -> 1 | E137: =E110 -> 2 | F137: =F110 -> 3 | G137: =G110 -> 4 | H137: =H110 -> 5 | I137: =I110 -> 6 | J137: =J110 -> 7 | K137: =K110 -> 8 | ... AH137: =AH110 -> 31
C138: Auto - Plan | D138: =SUM(D43:D48) -> 8.2258065 | E138: =SUM(E43:E48) -> 16.451613 | F138: =SUM(F43:F48) -> 24.677419 | G138: =SUM(G43:G48) -> 32.903226 | H138: =SUM(H43:H48) -> 41.129032 | I138: =SUM(I43:I48) -> 49.354839 | J138: =SUM(J43:J48) -> 57.580645 | K138: =SUM(K43:K48) -> 65.806452 | ... AH138: =SUM(AH43:AH48) -> 255
C139: Auto - Real | D139: =sum(D71:D76) -> 0 | E139: =sum(E71:E76) -> 6 | F139: =sum(F71:F76) -> 6 | G139: =sum(G71:G76) -> 6 | H139: =sum(H71:H76) -> 6 | I139: =sum(I71:I76) -> 6 | J139: =sum(J71:J76) -> 6 | K139: =sum(K71:K76) -> 6 | ... AH139: =sum(AH71:AH76) -> 110
C140: Personales - Plan | D140: =sum(D52:D55) -> 11.774194 | E140: =sum(E52:E55) -> 23.548387 | F140: =sum(F52:F55) -> 35.322581 | G140: =sum(G52:G55) -> 47.096774 | H140: =sum(H52:H55) -> 58.870968 | I140: =sum(I52:I55) -> 70.645161 | J140: =sum(J52:J55) -> 82.419355 | K140: =sum(K52:K55) -> 94.193548 | ... AH140: =sum(AH52:AH55) -> 365
C141: Personales - Real | D141: =sum(D80:D83) -> 131 | E141: =sum(E80:E83) -> 559.67 | F141: =sum(F80:F83) -> 559.67 | G141: =sum(G80:G83) -> 559.67 | H141: =sum(H80:H83) -> 559.67 | I141: =sum(I80:I83) -> 559.67 | J141: =sum(J80:J83) -> 559.67 | K141: =sum(K80:K83) -> 559.67 | ... AH141: =sum(AH80:AH83) -> 657.67
C144: Dia | D144: =D137 -> 1 | E144: =E137 -> 2 | F144: =F137 -> 3 | G144: =G137 -> 4 | H144: =H137 -> 5 | I144: =I137 -> 6 | J144: =J137 -> 7 | K144: =K137 -> 8 | ... AH144: =AH137 -> 31
C145: Pega - Plan | D145: =SUM(D49:D51) -> 14.703226 | E145: =SUM(E49:E51) -> 29.406452 | F145: =SUM(F49:F51) -> 44.109677 | G145: =SUM(G49:G51) -> 58.812903 | H145: =SUM(H49:H51) -> 73.516129 | I145: =SUM(I49:I51) -> 88.219355 | J145: =SUM(J49:J51) -> 102.92258 | K145: =SUM(K49:K51) -> 117.62581 | ... AH145: =SUM(AH49:AH51) -> 455.8
C146: Pega - Real | D146: =sum(D77:D79) -> 0 | E146: =sum(E77:E79) -> 0 | F146: =sum(F77:F79) -> 0 | G146: =sum(G77:G79) -> 0 | H146: =sum(H77:H79) -> 0 | I146: =sum(I77:I79) -> 0 | J146: =sum(J77:J79) -> 0 | K146: =sum(K77:K79) -> 0 | ... AH146: =sum(AH77:AH79) -> 291
C147: Transporte - Plan | D147: =sum(D41:D42) -> 5.483871 | E147: =sum(E41:E42) -> 10.967742 | F147: =sum(F41:F42) -> 16.451613 | G147: =sum(G41:G42) -> 21.935484 | H147: =sum(H41:H42) -> 27.419355 | I147: =sum(I41:I42) -> 32.903226 | J147: =sum(J41:J42) -> 38.387097 | K147: =sum(K41:K42) -> 43.870968 | ... AH147: =sum(AH41:AH42) -> 170
C148: Transporte - Real | D148: =sum(D69:D70) -> 0 | E148: =sum(E69:E70) -> 0 | F148: =sum(F69:F70) -> 0 | G148: =sum(G69:G70) -> 0 | H148: =sum(H69:H70) -> 0 | I148: =sum(I69:I70) -> 0 | J148: =sum(J69:J70) -> 3 | K148: =sum(K69:K70) -> 9 | ... AH148: =sum(AH69:AH70) -> 20
C188: Dia | D188: =D144 -> 1 | E188: =E144 -> 2 | F188: =F144 -> 3 | G188: =G144 -> 4 | H188: =H144 -> 5 | I188: =I144 -> 6 | J188: =J144 -> 7 | K188: =K144 -> 8 | ... AH188: =AH144 -> 31
C189: Total Costo Variable - Plan | D189: =sum(D56) -> 101.73548 | E189: =sum(E56) -> 203.47097 | F189: =sum(F56) -> 305.20645 | G189: =sum(G56) -> 406.94194 | H189: =sum(H56) -> 508.67742 | I189: =sum(I56) -> 610.4129 | J189: =sum(J56) -> 712.14839 | K189: =sum(K56) -> 813.88387 | ... AH189: =sum(AH56) -> 3153.8
C190: Total Costo Variable - Real | D190: =D84 -> 237 | E190: =E84 -> 820.67 | F190: =F84 -> 842.67 | G190: =G84 -> 927.67 | H190: =H84 -> 951.67 | I190: =I84 -> 951.67 | J190: =J84 -> 970.67 | K190: =K84 -> 1042.67 | ... AH190: =AH84 -> 2778.67
C192: Cumplimiento | D192: =AI84/MAX(D193:AI193) -> 0.8810546 | E192: =D192 -> 0.8810546 | F192: =E192 -> 0.8810546 | G192: =F192 -> 0.8810546 | H192: =G192 -> 0.8810546 | I192: =H192 -> 0.8810546 | J192: =I192 -> 0.8810546 | K192: =J192 -> 0.8810546 | L192: =K192 -> 0.8810546 | ... AI192: =AH192 -> 0.8810546
C193: Plan - MTD | D193: =if(D$188=$AJ$59,D56,0) -> 0 | E193: =if(E$188=$AJ$59,E56,0) -> 0 | F193: =if(F$188=$AJ$59,F56,0) -> 0 | G193: =if(G$188=$AJ$59,G56,0) -> 0 | H193: =if(H$188=$AJ$59,H56,0) -> 0 | I193: =if(I$188=$AJ$59,I56,0) -> 0 | J193: =if(J$188=$AJ$59,J56,0) -> 0 | K193: =if(K$188=$AJ$59,K56,0) -> 0 | ... AI193: =if(AI$188=$AJ$59,AI56,0) -> 0
B214: Diff Accumulado | C214: Dia | D214: 1 | E214: =D214+1 -> 2 | F214: =E214+1 -> 3 | G214: =F214+1 -> 4 | H214: =G214+1 -> 5 | I214: =H214+1 -> 6 | J214: =I214+1 -> 7 | K214: =J214+1 -> 8 | L214: =K214+1 -> 9 | ... AH214: =AG214+1 -> 31 | AI214: Total Mes | AJ214: Remanente
B215: Clasificacion | C215: SubClasificacion | AM215: MTD | AN215: Rem. Mes
B216: Costo Fijo - Depto | C216: Luz | AI216: =SUM(D216:AH216) -> 0 | AK216: Luz | AL216: Luz - Internet | AM216: =sum(D216:AH216, D217:AH217) -> -7 | AN216: =AJ217 -> -7
...
